{
  "name": "w06_a05_02.ks",
  "lines": [
    {
      "lineNumber": 9,
      "line": "@Talk name=和哉\r\n"
    },
    {
      "lineNumber": 10,
      "line": "「とはいえ……」\r\n"
    },
    {
      "lineNumber": 13,
      "line": "@Talk name=心の声\r\n"
    },
    {
      "lineNumber": 14,
      "line": "前と違って、いずみ姉さんの居場所の見当がまったく\r\n"
    },
    {
      "lineNumber": 15,
      "line": "つかない。\r\n"
    },
    {
      "lineNumber": 18,
      "line": "@Talk name=心の声\r\n"
    },
    {
      "lineNumber": 19,
      "line": "あの神社は夏祭り前の準備でまだ人が残っているだろうし、\r\n"
    },
    {
      "lineNumber": 20,
      "line": "そんな場所へ今のいずみ姉さんが行くとは思えない。\r\n"
    },
    {
      "lineNumber": 23,
      "line": "@Talk name=和哉\r\n"
    },
    {
      "lineNumber": 24,
      "line": "「でも、決めつけるのはよくないし……とりあえず、\r\n"
    },
    {
      "lineNumber": 25,
      "line": "　探してみよう」\r\n"
    },
    {
      "lineNumber": 28,
      "line": "@Talk name=心の声\r\n"
    },
    {
      "lineNumber": 29,
      "line": "こんな時間に、いずみ姉さんをひとりで居させるわけには\r\n"
    },
    {
      "lineNumber": 30,
      "line": "いかない。\r\n"
    },
    {
      "lineNumber": 33,
      "line": "@Talk name=和哉\r\n"
    },
    {
      "lineNumber": 34,
      "line": "俺は駆け足で、まずは神社へと向かっていった。\r\n"
    },
    {
      "lineNumber": 49,
      "line": "@Talk name=神主さん voice=NP260029\r\n"
    },
    {
      "lineNumber": 50,
      "line": "「……おや、会長さんの弟さんではないですか」\r\n"
    },
    {
      "lineNumber": 53,
      "line": "@Talk name=心の声\r\n"
    },
    {
      "lineNumber": 54,
      "line": "神社へ行ってみると、鳥居のところに神主さんが立って\r\n"
    },
    {
      "lineNumber": 55,
      "line": "いた。\r\n"
    },
    {
      "lineNumber": 58,
      "line": "@Talk name=和哉\r\n"
    },
    {
      "lineNumber": 59,
      "line": "「こんばんは」\r\n"
    },
    {
      "lineNumber": 62,
      "line": "@Talk name=神主さん voice=NP260030\r\n"
    },
    {
      "lineNumber": 63,
      "line": "「こんな時間にどうしたんですか？」\r\n"
    },
    {
      "lineNumber": 66,
      "line": "@Talk name=和哉\r\n"
    },
    {
      "lineNumber": 67,
      "line": "「いえ……まだ人が結構いるんですね」\r\n"
    },
    {
      "lineNumber": 70,
      "line": "@Talk name=神主さん voice=NP260031\r\n"
    },
    {
      "lineNumber": 71,
      "line": "「ええ、なにしろ祭りの前日ですからね」\r\n"
    },
    {
      "lineNumber": 75,
      "line": "@Talk name=心の声\r\n"
    },
    {
      "lineNumber": 76,
      "line": "社務所にはまだ明かりが灯っていて、なにやら騒いでいる\r\n"
    },
    {
      "lineNumber": 77,
      "line": "声がする。\r\n"
    },
    {
      "lineNumber": 80,
      "line": "@Talk name=神主さん voice=NP260032\r\n"
    },
    {
      "lineNumber": 81,
      "line": "「準備をしつつ、宴会を……いや、宴会をしつつ準備を\r\n"
    },
    {
      "lineNumber": 82,
      "line": "　しているんですよ」\r\n"
    },
    {
      "lineNumber": 85,
      "line": "@Talk name=和哉\r\n"
    },
    {
      "lineNumber": 86,
      "line": "「それは……楽しそうですね」\r\n"
    },
    {
      "lineNumber": 89,
      "line": "@Talk name=神主さん voice=NP260033\r\n"
    },
    {
      "lineNumber": 90,
      "line": "「君も参加していきますか？　酔っ払うのが嫌いで\r\n"
    },
    {
      "lineNumber": 91,
      "line": "　なければ、楽しめると思いますよ」\r\n"
    },
    {
      "lineNumber": 94,
      "line": "@Talk name=和哉\r\n"
    },
    {
      "lineNumber": 95,
      "line": "「今は遠慮しておきます」\r\n"
    },
    {
      "lineNumber": 98,
      "line": "@Talk name=心の声\r\n"
    },
    {
      "lineNumber": 99,
      "line": "この様子だと、聞くまでもなくいずみ姉さんはここには\r\n"
    },
    {
      "lineNumber": 100,
      "line": "来ていないようだ。\r\n"
    },
    {
      "lineNumber": 105,
      "line": "@Talk name=神主さん voice=NP260034\r\n"
    },
    {
      "lineNumber": 106,
      "line": "「ああ、そうだ弟さん」\r\n"
    },
    {
      "lineNumber": 109,
      "line": "@Talk name=和哉\r\n"
    },
    {
      "lineNumber": 110,
      "line": "「はい？」\r\n"
    },
    {
      "lineNumber": 115,
      "line": "@Talk name=心の声\r\n"
    },
    {
      "lineNumber": 116,
      "line": "早々に立ち去ろうとした俺を、神主さんが呼び止める。\r\n"
    },
    {
      "lineNumber": 119,
      "line": "@Talk name=神主さん voice=NP260035\r\n"
    },
    {
      "lineNumber": 120,
      "line": "「あなたたちのおかげで、今年は例年以上の良い祭りに\r\n"
    },
    {
      "lineNumber": 121,
      "line": "　なりそうです。ありがとうございます」\r\n"
    },
    {
      "lineNumber": 124,
      "line": "@Talk name=和哉\r\n"
    },
    {
      "lineNumber": 125,
      "line": "「いえ……こちらこそ、ありがとうございます」\r\n"
    },
    {
      "lineNumber": 128,
      "line": "@Talk name=神主さん voice=NP260036\r\n"
    },
    {
      "lineNumber": 129,
      "line": "「私どもが直接言うよりも、きっと君から聞くほうが\r\n"
    },
    {
      "lineNumber": 130,
      "line": "　会長さんの心にも響くことでしょう」\r\n"
    },
    {
      "lineNumber": 133,
      "line": "@Talk name=神主さん voice=NP260037\r\n"
    },
    {
      "lineNumber": 134,
      "line": "「感謝していると、どうぞ伝えておいてください」\r\n"
    },
    {
      "lineNumber": 137,
      "line": "@Talk name=和哉\r\n"
    },
    {
      "lineNumber": 138,
      "line": "「はい、必ず」\r\n"
    },
    {
      "lineNumber": 141,
      "line": "@Talk name=心の声\r\n"
    },
    {
      "lineNumber": 142,
      "line": "俺は神主さんにお辞儀をして、神社をあとにした。\r\n"
    },
    {
      "lineNumber": 153,
      "line": "@Talk name=薬局のお姉さん voice=NP330006\r\n"
    },
    {
      "lineNumber": 154,
      "line": "「あっ、和哉くんじゃない」\r\n"
    },
    {
      "lineNumber": 157,
      "line": "@Talk name=和哉\r\n"
    },
    {
      "lineNumber": 158,
      "line": "「あ、薬局の……どうしたんですか、こんな時間に？」\r\n"
    },
    {
      "lineNumber": 161,
      "line": "@Talk name=薬局のお姉さん voice=NP330007\r\n"
    },
    {
      "lineNumber": 162,
      "line": "「神社で騒いでるオジサマたちに、二日酔いに効くお薬を\r\n"
    },
    {
      "lineNumber": 163,
      "line": "　配りにいくのよ」\r\n"
    },
    {
      "lineNumber": 166,
      "line": "@Talk name=和哉\r\n"
    },
    {
      "lineNumber": 167,
      "line": "「ああ、なるほど……」\r\n"
    },
    {
      "lineNumber": 170,
      "line": "@Talk name=薬局のお姉さん voice=NP330008\r\n"
    },
    {
      "lineNumber": 171,
      "line": "「まあ、正規品じゃなくて店長オリジナルブレンドの\r\n"
    },
    {
      "lineNumber": 172,
      "line": "　漢方薬なんだけどね」\r\n"
    },
    {
      "lineNumber": 175,
      "line": "@Talk name=和哉\r\n"
    },
    {
      "lineNumber": 176,
      "line": "「それ、大丈夫なんですか……？」\r\n"
    },
    {
      "lineNumber": 179,
      "line": "@Talk name=薬局のお姉さん voice=NP330009\r\n"
    },
    {
      "lineNumber": 180,
      "line": "「騒いでいるオジサマの中にはうちの店長もいるから、\r\n"
    },
    {
      "lineNumber": 181,
      "line": "　最初に飲ませて様子を見るわ♪」\r\n"
    },
    {
      "lineNumber": 184,
      "line": "@Talk name=心の声\r\n"
    },
    {
      "lineNumber": 185,
      "line": "すごい力関係だな……\r\n"
    },
    {
      "lineNumber": 188,
      "line": "@Talk name=薬局のお姉さん voice=NP330010\r\n"
    },
    {
      "lineNumber": 189,
      "line": "「和哉くんはどうしたの？」\r\n"
    },
    {
      "lineNumber": 192,
      "line": "@Talk name=和哉\r\n"
    },
    {
      "lineNumber": 193,
      "line": "「あ、えっと……いずみ姉さんを見ませんでしたか？」\r\n"
    },
    {
      "lineNumber": 196,
      "line": "@Talk name=薬局のお姉さん voice=NP330011\r\n"
    },
    {
      "lineNumber": 197,
      "line": "「いずみちゃん？　見てないけど……」\r\n"
    },
    {
      "lineNumber": 200,
      "line": "@Talk name=薬局のお姉さん voice=NP330012\r\n"
    },
    {
      "lineNumber": 201,
      "line": "「女の子をこんな時間に一人で出歩かせるなんて、男の子\r\n"
    },
    {
      "lineNumber": 202,
      "line": "　失格だぞ〜？」\r\n"
    },
    {
      "lineNumber": 205,
      "line": "@Talk name=和哉\r\n"
    },
    {
      "lineNumber": 206,
      "line": "「重々承知してます」\r\n"
    },
    {
      "lineNumber": 209,
      "line": "@Talk name=薬局のお姉さん voice=NP330013\r\n"
    },
    {
      "lineNumber": 210,
      "line": "「ならよろしい。それじゃ、引き留めちゃ悪いよね、\r\n"
    },
    {
      "lineNumber": 211,
      "line": "　そろそろ行った方がいいよ」\r\n"
    },
    {
      "lineNumber": 214,
      "line": "@Talk name=和哉\r\n"
    },
    {
      "lineNumber": 215,
      "line": "「ありがとうございます……でも、お姉さんは大丈夫なん\r\n"
    },
    {
      "lineNumber": 216,
      "line": "　ですか？」\r\n"
    },
    {
      "lineNumber": 219,
      "line": "@Talk name=薬局のお姉さん voice=NP330014\r\n"
    },
    {
      "lineNumber": 220,
      "line": "「おお、いっぱしに心配してくれるんだ？」\r\n"
    },
    {
      "lineNumber": 223,
      "line": "@Talk name=和哉\r\n"
    },
    {
      "lineNumber": 224,
      "line": "「そりゃもちろん……」\r\n"
    },
    {
      "lineNumber": 227,
      "line": "@Talk name=薬局のお姉さん voice=NP330015\r\n"
    },
    {
      "lineNumber": 228,
      "line": "「よそ見するのも減点っ！　君が一人にしちゃ\r\n"
    },
    {
      "lineNumber": 229,
      "line": "　いけないのは、いずみちゃんでしょ！　ほら走るっ！」\r\n"
    },
    {
      "lineNumber": 234,
      "line": "@Talk name=和哉\r\n"
    },
    {
      "lineNumber": 235,
      "line": "「は、はいっ」\r\n"
    },
    {
      "lineNumber": 238,
      "line": "@Talk name=薬局のお姉さん voice=NP330016\r\n"
    },
    {
      "lineNumber": 239,
      "line": "「あはは、じゃ〜ね〜」\r\n"
    },
    {
      "lineNumber": 248,
      "line": "@Talk name=心の声\r\n"
    },
    {
      "lineNumber": 249,
      "line": "薬局のお姉さんの言葉に背中を押され、俺は商店街の中を\r\n"
    },
    {
      "lineNumber": 250,
      "line": "駆け抜けた。\r\n"
    },
    {
      "lineNumber": 260,
      "line": "@Talk name=心の声\r\n"
    },
    {
      "lineNumber": 261,
      "line": "そして……\r\n"
    },
    {
      "lineNumber": 265,
      "line": "@Talk name=心の声\r\n"
    },
    {
      "lineNumber": 266,
      "line": "とうとう俺は、たった一箇所、いずみ姉さんが居そうな\r\n"
    },
    {
      "lineNumber": 267,
      "line": "場所を思い至った。\r\n"
    },
    {
      "lineNumber": 271,
      "line": "@Talk name=心の声\r\n"
    },
    {
      "lineNumber": 272,
      "line": "そこは、いずみ姉さんが勉強以外の時間のほとんどを\r\n"
    },
    {
      "lineNumber": 273,
      "line": "費やしてきた、責任の象徴のような教室——\r\n"
    },
    {
      "lineNumber": 282,
      "line": "@Talk name=和哉\r\n"
    },
    {
      "lineNumber": 283,
      "line": "「いずみ姉さん、入るよ」\r\n"
    },
    {
      "lineNumber": 288,
      "line": "@Talk name=いずみ voice=IS010894\r\n"
    },
    {
      "lineNumber": 289,
      "line": "「…………っ！」\r\n"
    },
    {
      "lineNumber": 292,
      "line": "@Talk name=心の声\r\n"
    },
    {
      "lineNumber": 293,
      "line": "ノックをすると、部屋の中でかすかな物音がした。\r\n"
    },
    {
      "lineNumber": 305,
      "line": "@Talk name=心の声\r\n"
    },
    {
      "lineNumber": 306,
      "line": "返答を待たずに、俺は教室の扉を開いた。\r\n"
    },
    {
      "lineNumber": 309,
      "line": "@Talk name=和哉\r\n"
    },
    {
      "lineNumber": 310,
      "line": "「探したよ、いずみ姉さん」\r\n"
    },
    {
      "lineNumber": 316,
      "line": "@Talk name=いずみ voice=IS010895\r\n"
    },
    {
      "lineNumber": 317,
      "line": "「………………」\r\n"
    },
    {
      "lineNumber": 323,
      "line": "@Talk name=心の声\r\n"
    },
    {
      "lineNumber": 324,
      "line": "いずみ姉さんは、明かりも点けずに、窓辺にある\r\n"
    },
    {
      "lineNumber": 325,
      "line": "生徒会長の席にただ座っていた。\r\n"
    },
    {
      "lineNumber": 328,
      "line": "@Talk name=心の声\r\n"
    },
    {
      "lineNumber": 329,
      "line": "月明かりが艶やかな髪の毛や白い肌を照らして、まるで\r\n"
    },
    {
      "lineNumber": 330,
      "line": "夢の中に迷い込んだような錯覚を覚える。\r\n"
    },
    {
      "lineNumber": 335,
      "line": "@Talk name=和哉\r\n"
    },
    {
      "lineNumber": 336,
      "line": "「こんな時間に外をひとりで出歩くなんて危ないよ、\r\n"
    },
    {
      "lineNumber": 337,
      "line": "　姉さん」\r\n"
    },
    {
      "lineNumber": 343,
      "line": "@Talk name=いずみ voice=IS010896\r\n"
    },
    {
      "lineNumber": 344,
      "line": "「そんなことないわ、今日は明るいもの」\r\n"
    },
    {
      "lineNumber": 347,
      "line": "@Talk name=和哉\r\n"
    },
    {
      "lineNumber": 348,
      "line": "「お祭りの前日だからね」\r\n"
    },
    {
      "lineNumber": 354,
      "line": "@Talk name=いずみ voice=IS010897\r\n"
    },
    {
      "lineNumber": 355,
      "line": "「ええ……おかげで、神社へ逃げそびれたわ」\r\n"
    },
    {
      "lineNumber": 358,
      "line": "@Talk name=心の声\r\n"
    },
    {
      "lineNumber": 359,
      "line": "いずみ姉さんは自虐的な笑みを浮かべて、窓の外に目を\r\n"
    },
    {
      "lineNumber": 360,
      "line": "向けた。\r\n"
    },
    {
      "lineNumber": 363,
      "line": "@Talk name=和哉\r\n"
    },
    {
      "lineNumber": 364,
      "line": "「逃げる？」\r\n"
    },
    {
      "lineNumber": 370,
      "line": "@Talk name=いずみ voice=IS010898\r\n"
    },
    {
      "lineNumber": 371,
      "line": "「……ええ」\r\n"
    },
    {
      "lineNumber": 376,
      "line": "@Talk name=心の声\r\n"
    },
    {
      "lineNumber": 377,
      "line": "いずみ姉さんがためらいがちに頷くと、髪の毛が\r\n"
    },
    {
      "lineNumber": 378,
      "line": "さらさらと音を立てて流れた。\r\n"
    },
    {
      "lineNumber": 381,
      "line": "@Talk name=心の声\r\n"
    },
    {
      "lineNumber": 382,
      "line": "ひっそりとしていて、秘めやかで……いずみ姉さんが\r\n"
    },
    {
      "lineNumber": 383,
      "line": "とても神聖で、侵せない人のように思えた。\r\n"
    },
    {
      "lineNumber": 386,
      "line": "@Talk name=心の声\r\n"
    },
    {
      "lineNumber": 387,
      "line": "この感覚が、いずみ姉さんの壁なのか。\r\n"
    },
    {
      "lineNumber": 390,
      "line": "@Talk name=心の声\r\n"
    },
    {
      "lineNumber": 391,
      "line": "教室が暗いせいか、目に見えないものがはっきりと浮かび\r\n"
    },
    {
      "lineNumber": 392,
      "line": "あがってくるかのようだった。\r\n"
    },
    {
      "lineNumber": 397,
      "line": "@Talk name=いずみ voice=IS010899\r\n"
    },
    {
      "lineNumber": 398,
      "line": "「今日の激励会、見たでしょう？」\r\n"
    },
    {
      "lineNumber": 401,
      "line": "@Talk name=和哉\r\n"
    },
    {
      "lineNumber": 402,
      "line": "「うん、みんな楽しそうだったな」\r\n"
    },
    {
      "lineNumber": 408,
      "line": "@Talk name=いずみ voice=IS010900\r\n"
    },
    {
      "lineNumber": 409,
      "line": "「ええ、お祭りも楽しみにしてくれてるって言って、\r\n"
    },
    {
      "lineNumber": 410,
      "line": "　みんなが感謝してくれた」\r\n"
    },
    {
      "lineNumber": 413,
      "line": "@Talk name=和哉\r\n"
    },
    {
      "lineNumber": 414,
      "line": "「いいことだと思うよ」\r\n"
    },
    {
      "lineNumber": 419,
      "line": "@Talk name=いずみ voice=IS010901\r\n"
    },
    {
      "lineNumber": 420,
      "line": "「ええ、そうね……嬉しかったわ」\r\n"
    },
    {
      "lineNumber": 425,
      "line": "@Talk name=いずみ voice=IS010902\r\n"
    },
    {
      "lineNumber": 426,
      "line": "「でも……」\r\n"
    },
    {
      "lineNumber": 432,
      "line": "@Talk name=心の声\r\n"
    },
    {
      "lineNumber": 433,
      "line": "いずみ姉さんは自分の身体を抱き締めるようにして、\r\n"
    },
    {
      "lineNumber": 434,
      "line": "ぎゅっと身体を縮こまらせた。\r\n"
    },
    {
      "lineNumber": 439,
      "line": "@Talk name=いずみ voice=IS010903\r\n"
    },
    {
      "lineNumber": 440,
      "line": "「私が夏祭りを開催したかったのは、家族をひとつにする\r\n"
    },
    {
      "lineNumber": 441,
      "line": "　ためだったのよ」\r\n"
    },
    {
      "lineNumber": 446,
      "line": "@Talk name=いずみ voice=IS010904\r\n"
    },
    {
      "lineNumber": 447,
      "line": "「いちばん大事なことを失敗してしまうなんて……」\r\n"
    },
    {
      "lineNumber": 450,
      "line": "@Talk name=心の声\r\n"
    },
    {
      "lineNumber": 451,
      "line": "いずみ姉さんの吐息は、真冬のように震えていた。\r\n"
    },
    {
      "lineNumber": 456,
      "line": "@Talk name=いずみ voice=IS010905\r\n"
    },
    {
      "lineNumber": 457,
      "line": "「みんなが夏祭りを楽しみにしてくれているのに、私は\r\n"
    },
    {
      "lineNumber": 458,
      "line": "　明日が来るのが怖くて仕方がないのよ」\r\n"
    },
    {
      "lineNumber": 463,
      "line": "@Talk name=いずみ voice=IS010906\r\n"
    },
    {
      "lineNumber": 464,
      "line": "「怖くて、怖くて……どうしようもなくて、また逃げて\r\n"
    },
    {
      "lineNumber": 465,
      "line": "　しまったわ」\r\n"
    },
    {
      "lineNumber": 468,
      "line": "@Talk name=和哉\r\n"
    },
    {
      "lineNumber": 469,
      "line": "「いずみ姉さん……」\r\n"
    },
    {
      "lineNumber": 472,
      "line": "@Talk name=心の声\r\n"
    },
    {
      "lineNumber": 473,
      "line": "いずみ姉さんの苦痛に気付いていたにも関わらず、\r\n"
    },
    {
      "lineNumber": 474,
      "line": "直接支えることをしなかった自分を恨めしく思った。\r\n"
    },
    {
      "lineNumber": 479,
      "line": "@Talk name=心の声\r\n"
    },
    {
      "lineNumber": 480,
      "line": "一歩いずみ姉さんの方へ近づくと、床が大きく軋んで、\r\n"
    },
    {
      "lineNumber": 481,
      "line": "いずみ姉さんは肩を震わせた。\r\n"
    },
    {
      "lineNumber": 487,
      "line": "@Talk name=いずみ voice=IS010907\r\n"
    },
    {
      "lineNumber": 488,
      "line": "「誰かに頼るなんて、やっぱりだめだったんだわ、私……\r\n"
    },
    {
      "lineNumber": 489,
      "line": "　逃げるくせがまた戻ってきてしまったみたい」\r\n"
    },
    {
      "lineNumber": 494,
      "line": "@Talk name=いずみ voice=IS010908\r\n"
    },
    {
      "lineNumber": 495,
      "line": "「長女なんだって自分を律し続けないといけなかったの、\r\n"
    },
    {
      "lineNumber": 496,
      "line": "　だから……」\r\n"
    },
    {
      "lineNumber": 502,
      "line": "@Talk name=和哉\r\n"
    },
    {
      "lineNumber": 503,
      "line": "「いずみ姉さんっ」\r\n"
    },
    {
      "lineNumber": 508,
      "line": "@Talk name=心の声\r\n"
    },
    {
      "lineNumber": 509,
      "line": "いずみ姉さんが重ねる言葉に胸をえぐられる。\r\n"
    },
    {
      "lineNumber": 512,
      "line": "@Talk name=心の声\r\n"
    },
    {
      "lineNumber": 513,
      "line": "その痛みを超えるために、俺はいずみ姉さんを抱き締めて\r\n"
    },
    {
      "lineNumber": 514,
      "line": "いた。\r\n"
    },
    {
      "lineNumber": 522,
      "line": "@Talk name=いずみ voice=IS010909\r\n"
    },
    {
      "lineNumber": 523,
      "line": "「か……かずちゃん……？」\r\n"
    },
    {
      "lineNumber": 526,
      "line": "@Talk name=心の声\r\n"
    },
    {
      "lineNumber": 527,
      "line": "耳元でいずみ姉さんの呆然とした声が聞こえた。\r\n"
    },
    {
      "lineNumber": 530,
      "line": "@Talk name=心の声\r\n"
    },
    {
      "lineNumber": 531,
      "line": "それは紛れもなく、たったひとりの、か弱い女の子の\r\n"
    },
    {
      "lineNumber": 532,
      "line": "声だった。\r\n"
    },
    {
      "lineNumber": 535,
      "line": "@Talk name=和哉\r\n"
    },
    {
      "lineNumber": 536,
      "line": "「父さんのことは、俺が見つけたよ」\r\n"
    },
    {
      "lineNumber": 542,
      "line": "@Talk name=いずみ voice=IS010910\r\n"
    },
    {
      "lineNumber": 543,
      "line": "「ほ、本当に！？」\r\n"
    },
    {
      "lineNumber": 546,
      "line": "@Talk name=和哉\r\n"
    },
    {
      "lineNumber": 547,
      "line": "「ああ、明日の夕方までには帰ってくるって、約束して\r\n"
    },
    {
      "lineNumber": 548,
      "line": "　くれたよ」\r\n"
    },
    {
      "lineNumber": 554,
      "line": "@Talk name=いずみ voice=IS010911\r\n"
    },
    {
      "lineNumber": 555,
      "line": "「そう、なの……」\r\n"
    },
    {
      "lineNumber": 558,
      "line": "@Talk name=心の声\r\n"
    },
    {
      "lineNumber": 559,
      "line": "いずみ姉さんの身体から力が抜けていく。\r\n"
    },
    {
      "lineNumber": 566,
      "line": "@Talk name=いずみ voice=IS010912\r\n"
    },
    {
      "lineNumber": 567,
      "line": "「ありがとう、かずちゃん……」\r\n"
    },
    {
      "lineNumber": 570,
      "line": "@Talk name=心の声\r\n"
    },
    {
      "lineNumber": 571,
      "line": "耳にかかる吐息は熱く、震えている。\r\n"
    },
    {
      "lineNumber": 574,
      "line": "@Talk name=心の声\r\n"
    },
    {
      "lineNumber": 575,
      "line": "まるで今にも泣きだしそうだった。\r\n"
    },
    {
      "lineNumber": 578,
      "line": "@Talk name=和哉\r\n"
    },
    {
      "lineNumber": 579,
      "line": "「いずみ姉さんから見たら、俺は全然頼りないかもしれ\r\n"
    },
    {
      "lineNumber": 580,
      "line": "　ないけど……」\r\n"
    },
    {
      "lineNumber": 583,
      "line": "@Talk name=和哉\r\n"
    },
    {
      "lineNumber": 584,
      "line": "「いずみ姉さんのことを支えたいと思うし、支えられる\r\n"
    },
    {
      "lineNumber": 585,
      "line": "　ように最大限努力するよ」\r\n"
    },
    {
      "lineNumber": 590,
      "line": "@Talk name=いずみ voice=IS010913\r\n"
    },
    {
      "lineNumber": 591,
      "line": "「………………」\r\n"
    },
    {
      "lineNumber": 594,
      "line": "@Talk name=和哉\r\n"
    },
    {
      "lineNumber": 595,
      "line": "「いずみ姉さんが抱えきれないことは、俺にも持たせて\r\n"
    },
    {
      "lineNumber": 596,
      "line": "　ほしい」\r\n"
    },
    {
      "lineNumber": 599,
      "line": "@Talk name=和哉\r\n"
    },
    {
      "lineNumber": 600,
      "line": "「逃げ出す前に……いや、逃げ出す場所も、俺のとなりに\r\n"
    },
    {
      "lineNumber": 601,
      "line": "　してほしい」\r\n"
    },
    {
      "lineNumber": 606,
      "line": "@Talk name=心の声\r\n"
    },
    {
      "lineNumber": 607,
      "line": "心からの願いだった。\r\n"
    },
    {
      "lineNumber": 610,
      "line": "@Talk name=心の声\r\n"
    },
    {
      "lineNumber": 611,
      "line": "もう、一人で苦しむいずみ姉さんのことを見たくない。\r\n"
    },
    {
      "lineNumber": 614,
      "line": "@Talk name=心の声\r\n"
    },
    {
      "lineNumber": 615,
      "line": "それは、いずみ姉さんが俺の姉だからという以上に——\r\n"
    },
    {
      "lineNumber": 620,
      "line": "@Talk name=いずみ voice=IS010914\r\n"
    },
    {
      "lineNumber": 621,
      "line": "「なんだか、プロポーズみたいね」\r\n"
    },
    {
      "lineNumber": 624,
      "line": "@Talk name=心の声\r\n"
    },
    {
      "lineNumber": 625,
      "line": "驚きながらも、いずみ姉さんは笑ったようだった。\r\n"
    },
    {
      "lineNumber": 628,
      "line": "@Talk name=心の声\r\n"
    },
    {
      "lineNumber": 629,
      "line": "確かに、聞きようによってはそうかもしれない。\r\n"
    },
    {
      "lineNumber": 635,
      "line": "@Talk name=いずみ voice=IS010915\r\n"
    },
    {
      "lineNumber": 636,
      "line": "「……思い出したわ」\r\n"
    },
    {
      "lineNumber": 639,
      "line": "@Talk name=和哉\r\n"
    },
    {
      "lineNumber": 640,
      "line": "「え？」\r\n"
    },
    {
      "lineNumber": 645,
      "line": "@Talk name=いずみ voice=IS010916\r\n"
    },
    {
      "lineNumber": 646,
      "line": "「昔もかずちゃんに同じようなことを言われた思い出」\r\n"
    },
    {
      "lineNumber": 649,
      "line": "@Talk name=心の声\r\n"
    },
    {
      "lineNumber": 650,
      "line": "いずみ姉さんは、静かで暖かな声音で言った。\r\n"
    },
    {
      "lineNumber": 653,
      "line": "@Talk name=和哉\r\n"
    },
    {
      "lineNumber": 654,
      "line": "「この間の神社でも、似たようなことを言ってたね」\r\n"
    },
    {
      "lineNumber": 659,
      "line": "@Talk name=いずみ voice=IS010917\r\n"
    },
    {
      "lineNumber": 660,
      "line": "「大切な思い出だから、何度も思い出すのよ」\r\n"
    },
    {
      "lineNumber": 665,
      "line": "@Talk name=いずみ voice=IS010918\r\n"
    },
    {
      "lineNumber": 666,
      "line": "「でも、この間よりもっと、ちゃんと思い出したの」\r\n"
    },
    {
      "lineNumber": 669,
      "line": "@Talk name=和哉\r\n"
    },
    {
      "lineNumber": 670,
      "line": "「ちゃんとって……？」\r\n"
    },
    {
      "lineNumber": 675,
      "line": "@Talk name=いずみ voice=IS010919\r\n"
    },
    {
      "lineNumber": 676,
      "line": "「ずっと昔、家出をした私に『僕を頼って』って、\r\n"
    },
    {
      "lineNumber": 677,
      "line": "　かずちゃんが言ってくれたときに……」\r\n"
    },
    {
      "lineNumber": 683,
      "line": "@Talk name=いずみ voice=IS010920\r\n"
    },
    {
      "lineNumber": 684,
      "line": "「私は、そんなことを言ってくれる優しいかずちゃんの\r\n"
    },
    {
      "lineNumber": 685,
      "line": "　ためにも、ちゃんとした姉になろうと思ったの」\r\n"
    },
    {
      "lineNumber": 690,
      "line": "@Talk name=いずみ voice=IS010921\r\n"
    },
    {
      "lineNumber": 691,
      "line": "「強くなって、誰からも尊敬されるようになって、\r\n"
    },
    {
      "lineNumber": 692,
      "line": "　かずちゃんに対して恥ずかしくない『お姉ちゃん』に\r\n"
    },
    {
      "lineNumber": 693,
      "line": "　なろうと思ったのよ」\r\n"
    },
    {
      "lineNumber": 696,
      "line": "@Talk name=和哉\r\n"
    },
    {
      "lineNumber": 697,
      "line": "「あのころでも、いずみ姉さんは充分すごかったよ」\r\n"
    },
    {
      "lineNumber": 703,
      "line": "@Talk name=いずみ voice=IS010922\r\n"
    },
    {
      "lineNumber": 704,
      "line": "「……全然足りなかったわ」\r\n"
    },
    {
      "lineNumber": 709,
      "line": "@Talk name=いずみ voice=IS010923\r\n"
    },
    {
      "lineNumber": 710,
      "line": "「体育の授業に出たくないからって逃げだしたり、\r\n"
    },
    {
      "lineNumber": 711,
      "line": "　お夕飯のおかずが苦手だからって逃げだしたり……」\r\n"
    },
    {
      "lineNumber": 716,
      "line": "@Talk name=いずみ voice=IS010924\r\n"
    },
    {
      "lineNumber": 717,
      "line": "「みことちゃんとかずちゃんが仲良くしていると心が\r\n"
    },
    {
      "lineNumber": 718,
      "line": "　むずむずして、向こう見ずに喧嘩をしかけたりも\r\n"
    },
    {
      "lineNumber": 719,
      "line": "　してしまっていたし」\r\n"
    },
    {
      "lineNumber": 722,
      "line": "@Talk name=和哉\r\n"
    },
    {
      "lineNumber": 723,
      "line": "「そ、そうだっけ？」\r\n"
    },
    {
      "lineNumber": 729,
      "line": "@Talk name=いずみ voice=IS010925\r\n"
    },
    {
      "lineNumber": 730,
      "line": "「ええ、かずちゃんの取り合いはずーっと前から続いてた\r\n"
    },
    {
      "lineNumber": 731,
      "line": "　のよ」\r\n"
    },
    {
      "lineNumber": 734,
      "line": "@Talk name=和哉\r\n"
    },
    {
      "lineNumber": 735,
      "line": "「………………」\r\n"
    },
    {
      "lineNumber": 738,
      "line": "@Talk name=心の声\r\n"
    },
    {
      "lineNumber": 739,
      "line": "なんとなくそうとは思っていたけど、耳元で、こんなに\r\n"
    },
    {
      "lineNumber": 740,
      "line": "密着した状態で言われると恥ずかしい。\r\n"
    },
    {
      "lineNumber": 745,
      "line": "@Talk name=いずみ voice=IS010926\r\n"
    },
    {
      "lineNumber": 746,
      "line": "「私がどうして『かずちゃん』って呼んでいるか、考えた\r\n"
    },
    {
      "lineNumber": 747,
      "line": "　ことはある？」\r\n"
    },
    {
      "lineNumber": 750,
      "line": "@Talk name=和哉\r\n"
    },
    {
      "lineNumber": 751,
      "line": "「いや……でも、昔からそうだったよな？」\r\n"
    },
    {
      "lineNumber": 757,
      "line": "@Talk name=いずみ voice=IS010927\r\n"
    },
    {
      "lineNumber": 758,
      "line": "「ええ、かずちゃんが私のことを『姉さん』って\r\n"
    },
    {
      "lineNumber": 759,
      "line": "　呼ぶこともね」\r\n"
    },
    {
      "lineNumber": 762,
      "line": "@Talk name=心の声\r\n"
    },
    {
      "lineNumber": 763,
      "line": "いずみ姉さんは頷くと、まるでタイムカプセルでも\r\n"
    },
    {
      "lineNumber": 764,
      "line": "開ける時のような、気恥ずかしそうな微笑みを浮かべた。\r\n"
    },
    {
      "lineNumber": 769,
      "line": "@Talk name=いずみ voice=IS010928\r\n"
    },
    {
      "lineNumber": 770,
      "line": "「『姉ちゃん』って、ちゃん付けで呼ばれている\r\n"
    },
    {
      "lineNumber": 771,
      "line": "　みことちゃんの方が、親密な感じがして、\r\n"
    },
    {
      "lineNumber": 772,
      "line": "　うらやましかったからなのよ」\r\n"
    },
    {
      "lineNumber": 777,
      "line": "@Talk name=いずみ voice=IS010929\r\n"
    },
    {
      "lineNumber": 778,
      "line": "「そんな親密さが欲しくて、せめて私からは\r\n"
    },
    {
      "lineNumber": 779,
      "line": "　『かずちゃん』って……」\r\n"
    },
    {
      "lineNumber": 784,
      "line": "@Talk name=いずみ voice=IS010930\r\n"
    },
    {
      "lineNumber": 785,
      "line": "「ね、こんなささいなところでもライバル心を抱くくらい、\r\n"
    },
    {
      "lineNumber": 786,
      "line": "　ずっとかずちゃんのことが好きだったのよ」\r\n"
    },
    {
      "lineNumber": 789,
      "line": "@Talk name=和哉\r\n"
    },
    {
      "lineNumber": 790,
      "line": "「………………」\r\n"
    },
    {
      "lineNumber": 795,
      "line": "@Talk name=心の声\r\n"
    },
    {
      "lineNumber": 796,
      "line": "話しているうちに、いずみ姉さんの顔は真っ赤になって\r\n"
    },
    {
      "lineNumber": 797,
      "line": "いた。\r\n"
    },
    {
      "lineNumber": 802,
      "line": "@Talk name=心の声\r\n"
    },
    {
      "lineNumber": 803,
      "line": "けれどそれ以上に、俺の顔も赤くなっているはずだ。\r\n"
    },
    {
      "lineNumber": 806,
      "line": "@Talk name=心の声\r\n"
    },
    {
      "lineNumber": 807,
      "line": "これから、いずみ姉さんに呼びかけられるたびに、\r\n"
    },
    {
      "lineNumber": 808,
      "line": "今の話を思い出してしまうだろと思うと、たまらない。\r\n"
    },
    {
      "lineNumber": 811,
      "line": "@Talk name=心の声\r\n"
    },
    {
      "lineNumber": 812,
      "line": "恥ずかしさと嬉しさがまざった、ひどく甘酸っぱい\r\n"
    },
    {
      "lineNumber": 813,
      "line": "気持ちが胸に広がった。\r\n"
    },
    {
      "lineNumber": 818,
      "line": "@Talk name=いずみ voice=IS010931\r\n"
    },
    {
      "lineNumber": 819,
      "line": "「だからね、家出をするたびにかずちゃんが探しに来て\r\n"
    },
    {
      "lineNumber": 820,
      "line": "　くれると、かずちゃんを独り占めできるからとっても\r\n"
    },
    {
      "lineNumber": 821,
      "line": "　嬉しかったのだけど……」\r\n"
    },
    {
      "lineNumber": 826,
      "line": "@Talk name=いずみ voice=IS010932\r\n"
    },
    {
      "lineNumber": 827,
      "line": "「かずちゃんを困らせるお姉ちゃんからは卒業して、\r\n"
    },
    {
      "lineNumber": 828,
      "line": "　かずちゃんのことを助けられるお姉ちゃんになろうと\r\n"
    },
    {
      "lineNumber": 829,
      "line": "　思ったの」\r\n"
    },
    {
      "lineNumber": 834,
      "line": "@Talk name=いずみ voice=IS010933\r\n"
    },
    {
      "lineNumber": 835,
      "line": "「かずちゃんのことが、大好きだから……やきもち焼きな\r\n"
    },
    {
      "lineNumber": 836,
      "line": "　だけの自分を変えようと思ったのよ」\r\n"
    },
    {
      "lineNumber": 841,
      "line": "@Talk name=いずみ voice=IS010934\r\n"
    },
    {
      "lineNumber": 842,
      "line": "「私、目的を見失っていたわ……かずちゃんの呼び方と\r\n"
    },
    {
      "lineNumber": 843,
      "line": "　同じように、しっかり者のお姉ちゃんでいたいことにも、\r\n"
    },
    {
      "lineNumber": 844,
      "line": "　ちゃんと理由があったのに」\r\n"
    },
    {
      "lineNumber": 849,
      "line": "@Talk name=いずみ voice=IS010935\r\n"
    },
    {
      "lineNumber": 850,
      "line": "「私はまだまだ、全然だめね。かずちゃんがいないと\r\n"
    },
    {
      "lineNumber": 851,
      "line": "　なにもできないまま」\r\n"
    },
    {
      "lineNumber": 856,
      "line": "@Talk name=いずみ voice=IS010936\r\n"
    },
    {
      "lineNumber": 857,
      "line": "「こんな私じゃ、とてもじゃないけど……」\r\n"
    },
    {
      "lineNumber": 860,
      "line": "@Talk name=和哉\r\n"
    },
    {
      "lineNumber": 861,
      "line": "「いずみ姉さん」\r\n"
    },
    {
      "lineNumber": 864,
      "line": "@Talk name=和哉\r\n"
    },
    {
      "lineNumber": 865,
      "line": "「俺は、いずみ姉さんのやきもち焼きなところも、\r\n"
    },
    {
      "lineNumber": 866,
      "line": "　弱いところも、全部ひっくるめて好きになったんだよ」\r\n"
    },
    {
      "lineNumber": 872,
      "line": "@Talk name=いずみ voice=IS010937\r\n"
    },
    {
      "lineNumber": 873,
      "line": "「えっ……」\r\n"
    },
    {
      "lineNumber": 876,
      "line": "@Talk name=心の声\r\n"
    },
    {
      "lineNumber": 877,
      "line": "一度言葉にすると、思いがあふれてとまらなかった。\r\n"
    },
    {
      "lineNumber": 880,
      "line": "@Talk name=和哉\r\n"
    },
    {
      "lineNumber": 881,
      "line": "「確かに姉弟としてだけだったら、俺はいずみ姉さんの\r\n"
    },
    {
      "lineNumber": 882,
      "line": "　全てを支えることはできないかもしれないし……年長の\r\n"
    },
    {
      "lineNumber": 883,
      "line": "　いずみ姉さんに頼ることの方が多いかもしれない」\r\n"
    },
    {
      "lineNumber": 886,
      "line": "@Talk name=和哉\r\n"
    },
    {
      "lineNumber": 887,
      "line": "「でも俺は男として、いずみ姉さんのことを見ているん\r\n"
    },
    {
      "lineNumber": 888,
      "line": "　だよ」\r\n"
    },
    {
      "lineNumber": 891,
      "line": "@Talk name=和哉\r\n"
    },
    {
      "lineNumber": 892,
      "line": "「いずみ姉さんのことを、か弱くて、守ってあげたい、\r\n"
    },
    {
      "lineNumber": 893,
      "line": "　愛しい恋人だって思ってるんだ」\r\n"
    },
    {
      "lineNumber": 899,
      "line": "@Talk name=いずみ voice=IS010938\r\n"
    },
    {
      "lineNumber": 900,
      "line": "「…………っ」\r\n"
    },
    {
      "lineNumber": 903,
      "line": "@Talk name=心の声\r\n"
    },
    {
      "lineNumber": 904,
      "line": "腕の中で、いずみ姉さんの身体がぶるっと震えた。\r\n"
    },
    {
      "lineNumber": 910,
      "line": "@Talk name=いずみ voice=IS010939\r\n"
    },
    {
      "lineNumber": 911,
      "line": "「そ……そんなふうに、慰めようとしてくれなくても\r\n"
    },
    {
      "lineNumber": 912,
      "line": "　いいのよ」\r\n"
    },
    {
      "lineNumber": 917,
      "line": "@Talk name=いずみ voice=IS010940\r\n"
    },
    {
      "lineNumber": 918,
      "line": "「かずちゃんは、優しいから……いつでも私が欲しいと\r\n"
    },
    {
      "lineNumber": 919,
      "line": "　思う言葉をくれるから……だから……」\r\n"
    },
    {
      "lineNumber": 922,
      "line": "@Talk name=和哉\r\n"
    },
    {
      "lineNumber": 923,
      "line": "「こんなこと、気を遣っただけで言えるようなことじゃ\r\n"
    },
    {
      "lineNumber": 924,
      "line": "　ないよ」\r\n"
    },
    {
      "lineNumber": 927,
      "line": "@Talk name=和哉\r\n"
    },
    {
      "lineNumber": 928,
      "line": "「いずみ姉さんが好きだ……俺のすべてをかけて、\r\n"
    },
    {
      "lineNumber": 929,
      "line": "　支え続けたいと思うくらい」\r\n"
    },
    {
      "lineNumber": 934,
      "line": "@Talk name=いずみ voice=IS010941\r\n"
    },
    {
      "lineNumber": 935,
      "line": "「…………っ！」\r\n"
    },
    {
      "lineNumber": 941,
      "line": "@Talk name=いずみ voice=IS010942\r\n"
    },
    {
      "lineNumber": 942,
      "line": "「…………夢みたい……夢かしら？」\r\n"
    },
    {
      "lineNumber": 947,
      "line": "@Talk name=いずみ voice=IS010943\r\n"
    },
    {
      "lineNumber": 948,
      "line": "「かずちゃんが自分から私を抱きしめてくれるなんて、\r\n"
    },
    {
      "lineNumber": 949,
      "line": "　想像もつかなかったもの……あの時から、夢でも\r\n"
    },
    {
      "lineNumber": 950,
      "line": "　見ているのかしら？」\r\n"
    },
    {
      "lineNumber": 953,
      "line": "@Talk name=和哉\r\n"
    },
    {
      "lineNumber": 954,
      "line": "「そこまで疑われると、さすがに傷つく」\r\n"
    },
    {
      "lineNumber": 957,
      "line": "@Talk name=心の声\r\n"
    },
    {
      "lineNumber": 958,
      "line": "確かに今まで、優柔不断だったのは事実だけど。\r\n"
    },
    {
      "lineNumber": 963,
      "line": "@Talk name=いずみ voice=IS010944\r\n"
    },
    {
      "lineNumber": 964,
      "line": "「ふふっ……だって、うれしくて……」\r\n"
    },
    {
      "lineNumber": 972,
      "line": "@Talk name=心の声\r\n"
    },
    {
      "lineNumber": 973,
      "line": "いずみ姉さんが、ためらいがちに抱きしめ返してくる。\r\n"
    },
    {
      "lineNumber": 978,
      "line": "@Talk name=いずみ voice=IS010945\r\n"
    },
    {
      "lineNumber": 979,
      "line": "「本当に、夢じゃないのね……」\r\n"
    },
    {
      "lineNumber": 982,
      "line": "@Talk name=和哉\r\n"
    },
    {
      "lineNumber": 983,
      "line": "「ああ……」\r\n"
    },
    {
      "lineNumber": 988,
      "line": "@Talk name=いずみ voice=IS010946\r\n"
    },
    {
      "lineNumber": 989,
      "line": "「かずちゃん……」\r\n"
    },
    {
      "lineNumber": 992,
      "line": "@Talk name=心の声\r\n"
    },
    {
      "lineNumber": 993,
      "line": "いずみ姉さんは、俺の身体から少しだけ顔を離して、俺の\r\n"
    },
    {
      "lineNumber": 994,
      "line": "目を見つめた。\r\n"
    },
    {
      "lineNumber": 997,
      "line": "@Talk name=心の声\r\n"
    },
    {
      "lineNumber": 998,
      "line": "それがなにを意味するかは、もう分かっていた。\r\n"
    },
    {
      "lineNumber": 1006,
      "line": "@Talk name=いずみ voice=IS010947\r\n"
    },
    {
      "lineNumber": 1007,
      "line": "「んっ……」\r\n"
    },
    {
      "lineNumber": 1010,
      "line": "@Talk name=心の声\r\n"
    },
    {
      "lineNumber": 1011,
      "line": "自分からいずみ姉さんへなにかをするのは初めてだ。\r\n"
    },
    {
      "lineNumber": 1014,
      "line": "@Talk name=心の声\r\n"
    },
    {
      "lineNumber": 1015,
      "line": "キスをしながら、妙な感慨が俺の胸を満たしていった。\r\n"
    },
    {
      "lineNumber": 1020,
      "line": "@Talk name=いずみ voice=IS010948\r\n"
    },
    {
      "lineNumber": 1021,
      "line": "「ん、ちゅ……んん、ちゅぅ……」\r\n"
    },
    {
      "lineNumber": 1026,
      "line": "@Talk name=いずみ voice=IS010949\r\n"
    },
    {
      "lineNumber": 1027,
      "line": "「ふ……ぁん……ん、かずちゃん……んん……」\r\n"
    },
    {
      "lineNumber": 1030,
      "line": "@Talk name=心の声\r\n"
    },
    {
      "lineNumber": 1031,
      "line": "甘い吐息まじりに、いずみ姉さんが名前を呼んでくれる。\r\n"
    },
    {
      "lineNumber": 1035,
      "line": "@Talk name=心の声\r\n"
    },
    {
      "lineNumber": 1036,
      "line": "姉さんとして……そして、女の子としての声で、名前を\r\n"
    },
    {
      "lineNumber": 1037,
      "line": "呼んでくれる。\r\n"
    },
    {
      "lineNumber": 1040,
      "line": "@Talk name=和哉\r\n"
    },
    {
      "lineNumber": 1041,
      "line": "「いずみ姉さん……」\r\n"
    },
    {
      "lineNumber": 1046,
      "line": "@Talk name=いずみ voice=IS010950\r\n"
    },
    {
      "lineNumber": 1047,
      "line": "「ん、んっ……かずちゃん……」\r\n"
    },
    {
      "lineNumber": 1050,
      "line": "@Talk name=心の声\r\n"
    },
    {
      "lineNumber": 1051,
      "line": "唇を離して見つめあうと、いずみ姉さんは幸せそうな\r\n"
    },
    {
      "lineNumber": 1052,
      "line": "表情をかすかにくもらせた。\r\n"
    },
    {
      "lineNumber": 1058,
      "line": "@Talk name=いずみ voice=IS010951\r\n"
    },
    {
      "lineNumber": 1059,
      "line": "「かずちゃんと両想いになれるなんて、こんなにうれしい\r\n"
    },
    {
      "lineNumber": 1060,
      "line": "　ことが起きて……」\r\n"
    },
    {
      "lineNumber": 1065,
      "line": "@Talk name=いずみ voice=IS010952\r\n"
    },
    {
      "lineNumber": 1066,
      "line": "「でも、明日、お父さんとお母さんが仲直りしてくれなかっ\r\n"
    },
    {
      "lineNumber": 1067,
      "line": "　たらどうしましょう……」\r\n"
    },
    {
      "lineNumber": 1072,
      "line": "@Talk name=和哉\r\n"
    },
    {
      "lineNumber": 1073,
      "line": "「………………」\r\n"
    },
    {
      "lineNumber": 1076,
      "line": "@Talk name=心の声\r\n"
    },
    {
      "lineNumber": 1077,
      "line": "いずみ姉さんは、俺を抱く手にさらに力を込める。\r\n"
    },
    {
      "lineNumber": 1084,
      "line": "@Talk name=いずみ voice=IS010953\r\n"
    },
    {
      "lineNumber": 1085,
      "line": "「かずちゃんとは、もちろんだけど……ほかの誰とも\r\n"
    },
    {
      "lineNumber": 1086,
      "line": "　離れ離れになりたくないわ……」\r\n"
    },
    {
      "lineNumber": 1091,
      "line": "@Talk name=いずみ voice=IS010954\r\n"
    },
    {
      "lineNumber": 1092,
      "line": "「うまくいくかしら？　私、まだ大きな失敗を残しては\r\n"
    },
    {
      "lineNumber": 1093,
      "line": "　いないかしら？」\r\n"
    },
    {
      "lineNumber": 1098,
      "line": "@Talk name=いずみ voice=IS010955\r\n"
    },
    {
      "lineNumber": 1099,
      "line": "「まだ、明日が来るのが怖いわ……」\r\n"
    },
    {
      "lineNumber": 1102,
      "line": "@Talk name=心の声\r\n"
    },
    {
      "lineNumber": 1103,
      "line": "いずみ姉さんは小さなころに戻ったように、俺に体を\r\n"
    },
    {
      "lineNumber": 1104,
      "line": "もたせかけ、すがるように服を握りしめてくる。\r\n"
    },
    {
      "lineNumber": 1107,
      "line": "@Talk name=和哉\r\n"
    },
    {
      "lineNumber": 1108,
      "line": "「……大丈夫だよ」\r\n"
    },
    {
      "lineNumber": 1111,
      "line": "@Talk name=心の声\r\n"
    },
    {
      "lineNumber": 1112,
      "line": "俺は不安を取り除けるようにと、優しい声で囁く。\r\n"
    },
    {
      "lineNumber": 1117,
      "line": "@Talk name=いずみ voice=IS010956\r\n"
    },
    {
      "lineNumber": 1118,
      "line": "「かずちゃん……」\r\n"
    },
    {
      "lineNumber": 1121,
      "line": "@Talk name=和哉\r\n"
    },
    {
      "lineNumber": 1122,
      "line": "「いずみ姉さんの考えは誰から見てもすばらしいものだし、\r\n"
    },
    {
      "lineNumber": 1123,
      "line": "　もし足りない部分があったとしても、俺が助ける」\r\n"
    },
    {
      "lineNumber": 1126,
      "line": "@Talk name=和哉\r\n"
    },
    {
      "lineNumber": 1127,
      "line": "「だから、なにも心配いらないんだよ」\r\n"
    },
    {
      "lineNumber": 1133,
      "line": "@Talk name=いずみ voice=IS010957\r\n"
    },
    {
      "lineNumber": 1134,
      "line": "「そう、ね……かずちゃんがいてくれれば、きっと……」\r\n"
    },
    {
      "lineNumber": 1137,
      "line": "@Talk name=和哉\r\n"
    },
    {
      "lineNumber": 1138,
      "line": "「ああ、俺はずっといずみ姉さんと一緒にいるから……」\r\n"
    },
    {
      "lineNumber": 1143,
      "line": "@Talk name=いずみ voice=IS010958\r\n"
    },
    {
      "lineNumber": 1144,
      "line": "「本当に？」\r\n"
    },
    {
      "lineNumber": 1147,
      "line": "@Talk name=和哉\r\n"
    },
    {
      "lineNumber": 1148,
      "line": "「もちろん」\r\n"
    },
    {
      "lineNumber": 1154,
      "line": "@Talk name=いずみ voice=IS010959\r\n"
    },
    {
      "lineNumber": 1155,
      "line": "「はぁ……夢みたい……」\r\n"
    },
    {
      "lineNumber": 1158,
      "line": "@Talk name=和哉\r\n"
    },
    {
      "lineNumber": 1159,
      "line": "「まだ言ってる」\r\n"
    },
    {
      "lineNumber": 1164,
      "line": "@Talk name=いずみ voice=IS010960\r\n"
    },
    {
      "lineNumber": 1165,
      "line": "「仕方がないでしょう、私はとっても慎重派なんだもの」\r\n"
    },
    {
      "lineNumber": 1168,
      "line": "@Talk name=心の声\r\n"
    },
    {
      "lineNumber": 1169,
      "line": "いずみ姉さんは拗ねたように言う。\r\n"
    },
    {
      "lineNumber": 1172,
      "line": "@Talk name=和哉\r\n"
    },
    {
      "lineNumber": 1173,
      "line": "「そうだな……」\r\n"
    },
    {
      "lineNumber": 1178,
      "line": "@Talk name=心の声\r\n"
    },
    {
      "lineNumber": 1179,
      "line": "今までいずみ姉さんには、迫らせてばかりだった。\r\n"
    },
    {
      "lineNumber": 1182,
      "line": "@Talk name=心の声\r\n"
    },
    {
      "lineNumber": 1183,
      "line": "あいまいな気持ちのまま、愛情表現の最上級のことまで\r\n"
    },
    {
      "lineNumber": 1184,
      "line": "させてしまったし……\r\n"
    },
    {
      "lineNumber": 1191,
      "line": "@Talk name=いずみ voice=IS010961\r\n"
    },
    {
      "lineNumber": 1192,
      "line": "「ん……かずちゃん……？」\r\n"
    },
    {
      "lineNumber": 1195,
      "line": "@Talk name=心の声\r\n"
    },
    {
      "lineNumber": 1196,
      "line": "俺がいずみ姉さんを抱いていた腕をほどくと、不安そうな\r\n"
    },
    {
      "lineNumber": 1197,
      "line": "顔で首をかしげた。\r\n"
    },
    {
      "lineNumber": 1202,
      "line": "@Talk name=和哉\r\n"
    },
    {
      "lineNumber": 1203,
      "line": "「いずみ姉さんの不安を、今から全部取り除こうと思うん\r\n"
    },
    {
      "lineNumber": 1204,
      "line": "　だけど……いいかな？」\r\n"
    },
    {
      "lineNumber": 1209,
      "line": "@Talk name=いずみ voice=IS010962\r\n"
    },
    {
      "lineNumber": 1210,
      "line": "「それって……」\r\n"
    },
    {
      "lineNumber": 1213,
      "line": "@Talk name=心の声\r\n"
    },
    {
      "lineNumber": 1214,
      "line": "察しのいい愛しの姉は、夜目にも分かるくらいに顔を赤く\r\n"
    },
    {
      "lineNumber": 1215,
      "line": "した。\r\n"
    },
    {
      "lineNumber": 1221,
      "line": "@Talk name=いずみ voice=IS010963\r\n"
    },
    {
      "lineNumber": 1222,
      "line": "「で、でも待って、かずちゃん……私、心の準備が……」\r\n"
    },
    {
      "lineNumber": 1225,
      "line": "@Talk name=和哉\r\n"
    },
    {
      "lineNumber": 1226,
      "line": "「そんなのいらないよ、俺に任せてくれればいいから」\r\n"
    },
    {
      "lineNumber": 1232,
      "line": "@Talk name=いずみ voice=IS010964\r\n"
    },
    {
      "lineNumber": 1233,
      "line": "「ま、待ってかずちゃん、あっ……」\r\n"
    },
    {
      "lineNumber": 1240,
      "line": "@Talk name=心の声\r\n"
    },
    {
      "lineNumber": 1241,
      "line": "あわあわと戸惑っているいずみ姉さんを抱え上げ、\r\n"
    },
    {
      "lineNumber": 1242,
      "line": "俺は滑り込むようにして椅子に座った。\r\n"
    }
  ]
}