{
  "name": "w03_z07_c03.ks",
  "lines": [
    {
      "lineNumber": 13,
      "shouldShift": false,
      "shift": 0,
      "line": {
        "type": "Talk",
        "values": [
          {
            "key": "name",
            "value": "弥恵"
          },
          {
            "key": "voice",
            "value": "YE000568"
          }
        ]
      }
    },
    {
      "lineNumber": 14,
      "shouldShift": false,
      "shift": 0,
      "line": {
        "text": "「あれ、兄さんに智花姉さん？」\r\n"
      }
    },
    {
      "lineNumber": 23,
      "shouldShift": false,
      "shift": 0,
      "line": {
        "type": "Talk",
        "values": [
          {
            "key": "name",
            "value": "智花"
          },
          {
            "key": "voice",
            "value": "TM001068"
          }
        ]
      }
    },
    {
      "lineNumber": 24,
      "shouldShift": false,
      "shift": 0,
      "line": {
        "text": "「や、ややや弥恵っ！？」\r\n"
      }
    },
    {
      "lineNumber": 30,
      "shouldShift": false,
      "shift": 0,
      "line": {
        "type": "Talk",
        "values": [
          {
            "key": "name",
            "value": "心の声"
          }
        ]
      }
    },
    {
      "lineNumber": 31,
      "shouldShift": false,
      "shift": 0,
      "line": {
        "text": "いきなりリビングの扉が開き、弥恵がすたすたと入って\r\n"
      }
    },
    {
      "lineNumber": 32,
      "shouldShift": false,
      "shift": 0,
      "line": {
        "text": "きた。\r\n"
      }
    },
    {
      "lineNumber": 38,
      "shouldShift": false,
      "shift": 0,
      "line": {
        "type": "Talk",
        "values": [
          {
            "key": "name",
            "value": "絵麻"
          },
          {
            "key": "voice",
            "value": "EM000479"
          }
        ]
      }
    },
    {
      "lineNumber": 39,
      "shouldShift": false,
      "shift": 0,
      "line": {
        "text": "「晩ごはんぶり、です」\r\n"
      }
    },
    {
      "lineNumber": 42,
      "shouldShift": false,
      "shift": 0,
      "line": {
        "type": "Talk",
        "values": [
          {
            "key": "name",
            "value": "心の声"
          }
        ]
      }
    },
    {
      "lineNumber": 43,
      "shouldShift": false,
      "shift": 0,
      "line": {
        "text": "その後ろには、絵麻までついてきている。\r\n"
      }
    },
    {
      "lineNumber": 46,
      "shouldShift": false,
      "shift": 0,
      "line": {
        "type": "Talk",
        "values": [
          {
            "key": "name",
            "value": "和哉"
          }
        ]
      }
    },
    {
      "lineNumber": 47,
      "shouldShift": false,
      "shift": 0,
      "line": {
        "text": "「絵麻も……どっ、どうしたんだ、いきなり？」\r\n"
      }
    },
    {
      "lineNumber": 53,
      "shouldShift": false,
      "shift": 0,
      "line": {
        "type": "Talk",
        "values": [
          {
            "key": "name",
            "value": "弥恵"
          },
          {
            "key": "voice",
            "value": "YE000569"
          }
        ]
      }
    },
    {
      "lineNumber": 54,
      "shouldShift": false,
      "shift": 0,
      "line": {
        "text": "「ふぇっ、いきなりって言われても……なにか飲み物が\r\n"
      }
    },
    {
      "lineNumber": 55,
      "shouldShift": false,
      "shift": 0,
      "line": {
        "text": "　欲しくなったから、来ただけだよ？」\r\n"
      }
    },
    {
      "lineNumber": 61,
      "shouldShift": false,
      "shift": 0,
      "line": {
        "type": "Talk",
        "values": [
          {
            "key": "name",
            "value": "絵麻"
          },
          {
            "key": "voice",
            "value": "EM000480"
          }
        ]
      }
    },
    {
      "lineNumber": 62,
      "shouldShift": false,
      "shift": 0,
      "line": {
        "text": "「リビングに来るのに、いきなりもなにもない、です……」\r\n"
      }
    },
    {
      "lineNumber": 65,
      "shouldShift": false,
      "shift": 0,
      "line": {
        "type": "Talk",
        "values": [
          {
            "key": "name",
            "value": "心の声"
          }
        ]
      }
    },
    {
      "lineNumber": 66,
      "shouldShift": false,
      "shift": 0,
      "line": {
        "text": "ごもっともです。\r\n"
      }
    },
    {
      "lineNumber": 71,
      "shouldShift": false,
      "shift": 0,
      "line": {
        "type": "Talk",
        "values": [
          {
            "key": "name",
            "value": "心の声"
          }
        ]
      }
    },
    {
      "lineNumber": 72,
      "shouldShift": false,
      "shift": 0,
      "line": {
        "text": "焦る俺たちに対して、ごく普通の反応のまま、妹たちが\r\n"
      }
    },
    {
      "lineNumber": 73,
      "shouldShift": false,
      "shift": 0,
      "line": {
        "text": "こっちへ歩いてくる。\r\n"
      }
    },
    {
      "lineNumber": 78,
      "shouldShift": false,
      "shift": 0,
      "line": {
        "type": "Talk",
        "values": [
          {
            "key": "name",
            "value": "心の声"
          }
        ]
      }
    },
    {
      "lineNumber": 79,
      "shouldShift": false,
      "shift": 0,
      "line": {
        "text": "俺はとっさに、洗濯かごから何枚かを取り出して智花の\r\n"
      }
    },
    {
      "lineNumber": 80,
      "shouldShift": false,
      "shift": 0,
      "line": {
        "text": "ひざに散らした。\r\n"
      }
    },
    {
      "lineNumber": 89,
      "shouldShift": false,
      "shift": 0,
      "line": {
        "type": "Talk",
        "values": [
          {
            "key": "name",
            "value": "智花"
          },
          {
            "key": "voice",
            "value": "TM001069"
          }
        ]
      }
    },
    {
      "lineNumber": 90,
      "shouldShift": false,
      "shift": 0,
      "line": {
        "text": "「あっ……」\r\n"
      }
    },
    {
      "lineNumber": 95,
      "shouldShift": false,
      "shift": 0,
      "line": {
        "type": "Talk",
        "values": [
          {
            "key": "name",
            "value": "心の声"
          }
        ]
      }
    },
    {
      "lineNumber": 96,
      "shouldShift": false,
      "shift": 0,
      "line": {
        "text": "智花がはっとしたように俺を見て、それから膝の上の\r\n"
      }
    },
    {
      "lineNumber": 97,
      "shouldShift": false,
      "shift": 0,
      "line": {
        "text": "洗濯物にすがるように手を握りしめる。\r\n"
      }
    },
    {
      "lineNumber": 103,
      "shouldShift": false,
      "shift": 0,
      "line": {
        "type": "Talk",
        "values": [
          {
            "key": "name",
            "value": "弥恵"
          },
          {
            "key": "voice",
            "value": "YE000570"
          }
        ]
      }
    },
    {
      "lineNumber": 104,
      "shouldShift": false,
      "shift": 0,
      "line": {
        "text": "「あっ、洗濯物、たたんでくれてたんだね」\r\n"
      }
    },
    {
      "lineNumber": 110,
      "shouldShift": false,
      "shift": 0,
      "line": {
        "type": "Talk",
        "values": [
          {
            "key": "name",
            "value": "絵麻"
          },
          {
            "key": "voice",
            "value": "EM000481"
          }
        ]
      }
    },
    {
      "lineNumber": 111,
      "shouldShift": false,
      "shift": 0,
      "line": {
        "text": "「いつもありがとう、ございます」\r\n"
      }
    },
    {
      "lineNumber": 119,
      "shouldShift": false,
      "shift": 0,
      "line": {
        "type": "Talk",
        "values": [
          {
            "key": "name",
            "value": "智花"
          },
          {
            "key": "voice",
            "value": "TM001070"
          }
        ]
      }
    },
    {
      "lineNumber": 120,
      "shouldShift": false,
      "shift": 0,
      "line": {
        "text": "「う、ううん、いいのよ……」\r\n"
      }
    },
    {
      "lineNumber": 123,
      "shouldShift": false,
      "shift": 0,
      "line": {
        "type": "Talk",
        "values": [
          {
            "key": "name",
            "value": "心の声"
          }
        ]
      }
    },
    {
      "lineNumber": 124,
      "shouldShift": false,
      "shift": 0,
      "line": {
        "text": "智花がひきつった笑みを浮かべている。\r\n"
      }
    },
    {
      "lineNumber": 127,
      "shouldShift": false,
      "shift": 0,
      "line": {
        "type": "Talk",
        "values": [
          {
            "key": "name",
            "value": "心の声"
          }
        ]
      }
    },
    {
      "lineNumber": 128,
      "shouldShift": false,
      "shift": 0,
      "line": {
        "text": "だらだらと汗が流れているのは、さっきの余韻なのか、\r\n"
      }
    },
    {
      "lineNumber": 129,
      "shouldShift": false,
      "shift": 0,
      "line": {
        "text": "それとも冷や汗だろうか……俺も背中にじっとりと嫌な\r\n"
      }
    },
    {
      "lineNumber": 130,
      "shouldShift": false,
      "shift": 0,
      "line": {
        "text": "汗をかいているので、冷や汗説の方が濃厚だ。\r\n"
      }
    },
    {
      "lineNumber": 137,
      "shouldShift": false,
      "shift": 0,
      "line": {
        "type": "Talk",
        "values": [
          {
            "key": "name",
            "value": "絵麻"
          },
          {
            "key": "voice",
            "value": "EM000482"
          }
        ]
      }
    },
    {
      "lineNumber": 138,
      "shouldShift": false,
      "shift": 0,
      "line": {
        "text": "「じー……」\r\n"
      }
    },
    {
      "lineNumber": 143,
      "shouldShift": false,
      "shift": 0,
      "line": {
        "type": "Talk",
        "values": [
          {
            "key": "name",
            "value": "絵麻"
          },
          {
            "key": "voice",
            "value": "EM000483"
          }
        ]
      }
    },
    {
      "lineNumber": 144,
      "shouldShift": false,
      "shift": 0,
      "line": {
        "text": "「……リビング、暑い……ですか？」\r\n"
      }
    },
    {
      "lineNumber": 153,
      "shouldShift": false,
      "shift": 0,
      "line": {
        "type": "Talk",
        "values": [
          {
            "key": "name",
            "value": "智花"
          },
          {
            "key": "voice",
            "value": "TM001071"
          }
        ]
      }
    },
    {
      "lineNumber": 154,
      "shouldShift": false,
      "shift": 0,
      "line": {
        "text": "「にゃぇえっ！？」\r\n"
      }
    },
    {
      "lineNumber": 161,
      "shouldShift": false,
      "shift": 0,
      "line": {
        "type": "Talk",
        "values": [
          {
            "key": "name",
            "value": "弥恵"
          },
          {
            "key": "voice",
            "value": "YE000571"
          }
        ]
      }
    },
    {
      "lineNumber": 162,
      "shouldShift": false,
      "shift": 0,
      "line": {
        "text": "「そうかな？　ひやってして逆に寒いくらいだけど……」\r\n"
      }
    },
    {
      "lineNumber": 165,
      "shouldShift": false,
      "shift": 0,
      "line": {
        "type": "Talk",
        "values": [
          {
            "key": "name",
            "value": "心の声"
          }
        ]
      }
    },
    {
      "lineNumber": 166,
      "shouldShift": false,
      "shift": 0,
      "line": {
        "text": "弥恵が無邪気に首を傾げ、俺たちの方を見る。\r\n"
      }
    },
    {
      "lineNumber": 171,
      "shouldShift": false,
      "shift": 0,
      "line": {
        "type": "Talk",
        "values": [
          {
            "key": "name",
            "value": "弥恵"
          },
          {
            "key": "voice",
            "value": "YE000572"
          }
        ]
      }
    },
    {
      "lineNumber": 172,
      "shouldShift": false,
      "shift": 0,
      "line": {
        "text": "「あれ、智花姉さんも兄さんもすごい汗……」\r\n"
      }
    },
    {
      "lineNumber": 175,
      "shouldShift": false,
      "shift": 0,
      "line": {
        "type": "Talk",
        "values": [
          {
            "key": "name",
            "value": "和哉"
          }
        ]
      }
    },
    {
      "lineNumber": 176,
      "shouldShift": false,
      "shift": 0,
      "line": {
        "text": "「も、もくもくと洗濯物をたたんでいたからな、集中して\r\n"
      }
    },
    {
      "lineNumber": 177,
      "shouldShift": false,
      "shift": 0,
      "line": {
        "text": "　暑くなったんだよ」\r\n"
      }
    },
    {
      "lineNumber": 183,
      "shouldShift": false,
      "shift": 0,
      "line": {
        "type": "Talk",
        "values": [
          {
            "key": "name",
            "value": "智花"
          },
          {
            "key": "voice",
            "value": "TM001072"
          }
        ]
      }
    },
    {
      "lineNumber": 184,
      "shouldShift": false,
      "shift": 0,
      "line": {
        "text": "「そそそうよ、うん、もう周りが見えないくらい\r\n"
      }
    },
    {
      "lineNumber": 185,
      "shouldShift": false,
      "shift": 0,
      "line": {
        "text": "　集中してたからよ、うん、絶対そう」\r\n"
      }
    },
    {
      "lineNumber": 190,
      "shouldShift": false,
      "shift": 0,
      "line": {
        "type": "Talk",
        "values": [
          {
            "key": "name",
            "value": "弥恵"
          },
          {
            "key": "voice",
            "value": "YE000573"
          }
        ]
      }
    },
    {
      "lineNumber": 191,
      "shouldShift": false,
      "shift": 0,
      "line": {
        "text": "「そ、そっかぁ……」\r\n"
      }
    },
    {
      "lineNumber": 197,
      "shouldShift": false,
      "shift": 0,
      "line": {
        "type": "Talk",
        "values": [
          {
            "key": "name",
            "value": "絵麻"
          },
          {
            "key": "voice",
            "value": "EM000484"
          }
        ]
      }
    },
    {
      "lineNumber": 198,
      "shouldShift": false,
      "shift": 0,
      "line": {
        "text": "「じー……」\r\n"
      }
    },
    {
      "lineNumber": 203,
      "shouldShift": false,
      "shift": 0,
      "line": {
        "type": "Talk",
        "values": [
          {
            "key": "name",
            "value": "心の声"
          }
        ]
      }
    },
    {
      "lineNumber": 204,
      "shouldShift": false,
      "shift": 0,
      "line": {
        "text": "今の言い訳は、さすがに苦しかっただろうか……？\r\n"
      }
    },
    {
      "lineNumber": 207,
      "shouldShift": false,
      "shift": 0,
      "line": {
        "type": "Talk",
        "values": [
          {
            "key": "name",
            "value": "心の声"
          }
        ]
      }
    },
    {
      "lineNumber": 208,
      "shouldShift": false,
      "shift": 0,
      "line": {
        "text": "しかし、こうなったらもうこれで押し通し、誤魔化すしか\r\n"
      }
    },
    {
      "lineNumber": 209,
      "shouldShift": false,
      "shift": 0,
      "line": {
        "text": "ない！\r\n"
      }
    },
    {
      "lineNumber": 214,
      "shouldShift": false,
      "shift": 0,
      "line": {
        "type": "Talk",
        "values": [
          {
            "key": "name",
            "value": "弥恵"
          },
          {
            "key": "voice",
            "value": "YE000574"
          }
        ]
      }
    },
    {
      "lineNumber": 215,
      "shouldShift": false,
      "shift": 0,
      "line": {
        "text": "「えっと……クーラーの温度、もう少し下げる？」\r\n"
      }
    },
    {
      "lineNumber": 218,
      "shouldShift": false,
      "shift": 0,
      "line": {
        "type": "Talk",
        "values": [
          {
            "key": "name",
            "value": "和哉"
          }
        ]
      }
    },
    {
      "lineNumber": 219,
      "shouldShift": false,
      "shift": 0,
      "line": {
        "text": "「いや、大丈夫だ。それより飲み物を取りにきたんじゃ\r\n"
      }
    },
    {
      "lineNumber": 220,
      "shouldShift": false,
      "shift": 0,
      "line": {
        "text": "　ないのか？」\r\n"
      }
    },
    {
      "lineNumber": 225,
      "shouldShift": false,
      "shift": 0,
      "line": {
        "type": "Talk",
        "values": [
          {
            "key": "name",
            "value": "弥恵"
          },
          {
            "key": "voice",
            "value": "YE000575"
          }
        ]
      }
    },
    {
      "lineNumber": 226,
      "shouldShift": false,
      "shift": 0,
      "line": {
        "text": "「あっ、うん、でも……」\r\n"
      }
    },
    {
      "lineNumber": 232,
      "shouldShift": false,
      "shift": 0,
      "line": {
        "type": "Talk",
        "values": [
          {
            "key": "name",
            "value": "心の声"
          }
        ]
      }
    },
    {
      "lineNumber": 233,
      "shouldShift": false,
      "shift": 0,
      "line": {
        "text": "弥恵と絵麻は顔を見合わせた。\r\n"
      }
    },
    {
      "lineNumber": 239,
      "shouldShift": false,
      "shift": 0,
      "line": {
        "type": "Talk",
        "values": [
          {
            "key": "name",
            "value": "弥恵"
          },
          {
            "key": "voice",
            "value": "YE000576"
          }
        ]
      }
    },
    {
      "lineNumber": 240,
      "shouldShift": false,
      "shift": 0,
      "line": {
        "text": "「もし良かったら、たたむの手伝うよ」\r\n"
      }
    },
    {
      "lineNumber": 246,
      "shouldShift": false,
      "shift": 0,
      "line": {
        "type": "Talk",
        "values": [
          {
            "key": "name",
            "value": "絵麻"
          },
          {
            "key": "voice",
            "value": "EM000485"
          }
        ]
      }
    },
    {
      "lineNumber": 247,
      "shouldShift": false,
      "shift": 0,
      "line": {
        "text": "「はい」\r\n"
      }
    },
    {
      "lineNumber": 255,
      "shouldShift": false,
      "shift": 0,
      "line": {
        "type": "Talk",
        "values": [
          {
            "key": "name",
            "value": "心の声"
          }
        ]
      }
    },
    {
      "lineNumber": 256,
      "shouldShift": false,
      "shift": 0,
      "line": {
        "text": "純真無垢な瞳が四つ。\r\n"
      }
    },
    {
      "lineNumber": 264,
      "shouldShift": false,
      "shift": 0,
      "line": {
        "type": "Talk",
        "values": [
          {
            "key": "name",
            "value": "無音/智花"
          }
        ]
      }
    },
    {
      "lineNumber": 265,
      "shouldShift": false,
      "shift": 0,
      "line": {
        "text": "「………………」\r\n"
      }
    },
    {
      "lineNumber": 268,
      "shouldShift": false,
      "shift": 0,
      "line": {
        "type": "Talk",
        "values": [
          {
            "key": "name",
            "value": "心の声"
          }
        ]
      }
    },
    {
      "lineNumber": 269,
      "shouldShift": false,
      "shift": 0,
      "line": {
        "text": "俺たちもまた、顔を見合わせる。\r\n"
      }
    },
    {
      "lineNumber": 274,
      "shouldShift": false,
      "shift": 0,
      "line": {
        "type": "Talk",
        "values": [
          {
            "key": "name",
            "value": "和哉"
          }
        ]
      }
    },
    {
      "lineNumber": 275,
      "shouldShift": false,
      "shift": 0,
      "line": {
        "text": "「大丈夫だよ。ここにあるの、ほとんど俺たちの\r\n"
      }
    },
    {
      "lineNumber": 276,
      "shouldShift": false,
      "shift": 0,
      "line": {
        "text": "　服だもんな？」\r\n"
      }
    },
    {
      "lineNumber": 282,
      "shouldShift": false,
      "shift": 0,
      "line": {
        "type": "Talk",
        "values": [
          {
            "key": "name",
            "value": "智花"
          },
          {
            "key": "voice",
            "value": "TM001073"
          }
        ]
      }
    },
    {
      "lineNumber": 283,
      "shouldShift": false,
      "shift": 0,
      "line": {
        "text": "「そっ、そうなの。うん、少なくとも、自分のことは\r\n"
      }
    },
    {
      "lineNumber": 284,
      "shouldShift": false,
      "shift": 0,
      "line": {
        "text": "　自分でやらないとね」\r\n"
      }
    },
    {
      "lineNumber": 290,
      "shouldShift": false,
      "shift": 0,
      "line": {
        "type": "Talk",
        "values": [
          {
            "key": "name",
            "value": "絵麻"
          },
          {
            "key": "voice",
            "value": "EM000486"
          }
        ]
      }
    },
    {
      "lineNumber": 291,
      "shouldShift": false,
      "shift": 0,
      "line": {
        "text": "「でも、ともかお姉ちゃんが持っているブラ……」\r\n"
      }
    },
    {
      "lineNumber": 296,
      "shouldShift": false,
      "shift": 0,
      "line": {
        "type": "Talk",
        "values": [
          {
            "key": "name",
            "value": "智花"
          },
          {
            "key": "voice",
            "value": "TM001074"
          }
        ]
      }
    },
    {
      "lineNumber": 297,
      "shouldShift": false,
      "shift": 0,
      "line": {
        "text": "「え？　……あ……」\r\n"
      }
    },
    {
      "lineNumber": 302,
      "shouldShift": false,
      "shift": 0,
      "line": {
        "type": "Talk",
        "values": [
          {
            "key": "name",
            "value": "心の声"
          }
        ]
      }
    },
    {
      "lineNumber": 303,
      "shouldShift": false,
      "shift": 0,
      "line": {
        "text": "カップのサイズがとても大きいのに、妙に可愛らしい\r\n"
      }
    },
    {
      "lineNumber": 304,
      "shouldShift": false,
      "shift": 0,
      "line": {
        "text": "パンダ模様のブラジャーが、智花の膝の上に\r\n"
      }
    },
    {
      "lineNumber": 305,
      "shouldShift": false,
      "shift": 0,
      "line": {
        "text": "ちょこんと載っている。\r\n"
      }
    },
    {
      "lineNumber": 313,
      "shouldShift": false,
      "shift": 0,
      "line": {
        "type": "Talk",
        "values": [
          {
            "key": "name",
            "value": "弥恵"
          },
          {
            "key": "voice",
            "value": "YE000577"
          }
        ]
      }
    },
    {
      "lineNumber": 314,
      "shouldShift": false,
      "shift": 0,
      "line": {
        "text": "「ひゃぁぁあああああああっ！？\r\n"
      }
    },
    {
      "lineNumber": 315,
      "shouldShift": false,
      "shift": 0,
      "line": {
        "text": "　ぁ、だ、だ、だ、だめぇぇぇぇぇぇぇええええっ！？」\r\n"
      }
    },
    {
      "lineNumber": 320,
      "shouldShift": false,
      "shift": 0,
      "line": {
        "type": "Talk",
        "values": [
          {
            "key": "name",
            "value": "心の声"
          }
        ]
      }
    },
    {
      "lineNumber": 321,
      "shouldShift": false,
      "shift": 0,
      "line": {
        "text": "弥恵が耳まで真っ赤に染めながら、智花の方へと\r\n"
      }
    },
    {
      "lineNumber": 322,
      "shouldShift": false,
      "shift": 0,
      "line": {
        "text": "駆けよろうとする。\r\n"
      }
    },
    {
      "lineNumber": 330,
      "shouldShift": false,
      "shift": 0,
      "line": {
        "type": "Talk",
        "values": [
          {
            "key": "name",
            "value": "智花"
          },
          {
            "key": "voice",
            "value": "TM001075"
          }
        ]
      }
    },
    {
      "lineNumber": 331,
      "shouldShift": false,
      "shift": 0,
      "line": {
        "text": "「きゃ、や、弥恵っ——！？」\r\n"
      }
    },
    {
      "lineNumber": 339,
      "shouldShift": false,
      "shift": 0,
      "line": {
        "type": "Talk",
        "values": [
          {
            "key": "name",
            "value": "和哉"
          }
        ]
      }
    },
    {
      "lineNumber": 340,
      "shouldShift": false,
      "shift": 0,
      "line": {
        "text": "「ちょ、ちょっと待った！」\r\n"
      }
    },
    {
      "lineNumber": 353,
      "shouldShift": false,
      "shift": 0,
      "line": {
        "type": "Talk",
        "values": [
          {
            "key": "name",
            "value": "弥恵"
          },
          {
            "key": "voice",
            "value": "YE000578"
          }
        ]
      }
    },
    {
      "lineNumber": 354,
      "shouldShift": false,
      "shift": 0,
      "line": {
        "text": "「ひゃわわわわっ！？」\r\n"
      }
    },
    {
      "lineNumber": 357,
      "shouldShift": false,
      "shift": 0,
      "line": {
        "type": "Talk",
        "values": [
          {
            "key": "name",
            "value": "心の声"
          }
        ]
      }
    },
    {
      "lineNumber": 358,
      "shouldShift": false,
      "shift": 0,
      "line": {
        "text": "すんでの所で、弥恵を後ろから抱き留める。\r\n"
      }
    },
    {
      "lineNumber": 366,
      "shouldShift": false,
      "shift": 0,
      "line": {
        "type": "Talk",
        "values": [
          {
            "key": "name",
            "value": "弥恵"
          },
          {
            "key": "voice",
            "value": "YE000579"
          }
        ]
      }
    },
    {
      "lineNumber": 367,
      "shouldShift": false,
      "shift": 0,
      "line": {
        "text": "「に、ににに、兄さん！？」\r\n"
      }
    },
    {
      "lineNumber": 370,
      "shouldShift": false,
      "shift": 0,
      "line": {
        "type": "Talk",
        "values": [
          {
            "key": "name",
            "value": "和哉"
          }
        ]
      }
    },
    {
      "lineNumber": 371,
      "shouldShift": false,
      "shift": 0,
      "line": {
        "text": "「弥恵は俺に見られるのが恥ずかしいんだろう？\r\n"
      }
    },
    {
      "lineNumber": 372,
      "shouldShift": false,
      "shift": 0,
      "line": {
        "text": "　だったらほら、俺が飲み物入れにいくから、な？\r\n"
      }
    },
    {
      "lineNumber": 373,
      "shouldShift": false,
      "shift": 0,
      "line": {
        "text": "　さぁ、落ち着こう」\r\n"
      }
    },
    {
      "lineNumber": 379,
      "shouldShift": false,
      "shift": 0,
      "line": {
        "type": "Talk",
        "values": [
          {
            "key": "name",
            "value": "弥恵"
          },
          {
            "key": "voice",
            "value": "YE000580"
          }
        ]
      }
    },
    {
      "lineNumber": 380,
      "shouldShift": false,
      "shift": 0,
      "line": {
        "text": "「ふぇっ、ぁ、あぅぅっ……」\r\n"
      }
    },
    {
      "lineNumber": 383,
      "shouldShift": false,
      "shift": 0,
      "line": {
        "type": "Talk",
        "values": [
          {
            "key": "name",
            "value": "心の声"
          }
        ]
      }
    },
    {
      "lineNumber": 384,
      "shouldShift": false,
      "shift": 0,
      "line": {
        "text": "大人しくなったものの、今度は目をぐるぐる回し始める\r\n"
      }
    },
    {
      "lineNumber": 385,
      "shouldShift": false,
      "shift": 0,
      "line": {
        "text": "弥恵。\r\n"
      }
    },
    {
      "lineNumber": 391,
      "shouldShift": false,
      "shift": 0,
      "line": {
        "type": "Talk",
        "values": [
          {
            "key": "name",
            "value": "弥恵"
          },
          {
            "key": "voice",
            "value": "YE000581"
          }
        ]
      }
    },
    {
      "lineNumber": 392,
      "shouldShift": false,
      "shift": 0,
      "line": {
        "text": "「はぅ、はぁぅ……うう……………きゅう。」\r\n"
      }
    },
    {
      "lineNumber": 398,
      "shouldShift": false,
      "shift": 0,
      "line": {
        "type": "Talk",
        "values": [
          {
            "key": "name",
            "value": "心の声"
          }
        ]
      }
    },
    {
      "lineNumber": 399,
      "shouldShift": false,
      "shift": 0,
      "line": {
        "text": "気の抜けるような声と共に、弥恵の力が一気に抜けた。\r\n"
      }
    },
    {
      "lineNumber": 404,
      "shouldShift": false,
      "shift": 0,
      "line": {
        "type": "Talk",
        "values": [
          {
            "key": "name",
            "value": "和哉"
          }
        ]
      }
    },
    {
      "lineNumber": 405,
      "shouldShift": false,
      "shift": 0,
      "line": {
        "text": "「あ、あれ？　弥恵？　弥恵？」\r\n"
      }
    },
    {
      "lineNumber": 412,
      "shouldShift": false,
      "shift": 0,
      "line": {
        "type": "Talk",
        "values": [
          {
            "key": "name",
            "value": "絵麻"
          },
          {
            "key": "voice",
            "value": "EM000487"
          }
        ]
      }
    },
    {
      "lineNumber": 413,
      "shouldShift": false,
      "shift": 0,
      "line": {
        "text": "「お兄ちゃん……ぐっどじょぶ、です」\r\n"
      }
    },
    {
      "lineNumber": 418,
      "shouldShift": false,
      "shift": 0,
      "line": {
        "type": "Talk",
        "values": [
          {
            "key": "name",
            "value": "心の声"
          }
        ]
      }
    },
    {
      "lineNumber": 419,
      "shouldShift": false,
      "shift": 0,
      "line": {
        "text": "なぜか絵麻が親指を立てる。\r\n"
      }
    },
    {
      "lineNumber": 424,
      "shouldShift": false,
      "shift": 0,
      "line": {
        "type": "Talk",
        "values": [
          {
            "key": "name",
            "value": "絵麻"
          },
          {
            "key": "voice",
            "value": "EM000488"
          }
        ]
      }
    },
    {
      "lineNumber": 425,
      "shouldShift": false,
      "shift": 0,
      "line": {
        "text": "「お姉ちゃん、お部屋に運んでくれます、か？」\r\n"
      }
    },
    {
      "lineNumber": 428,
      "shouldShift": false,
      "shift": 0,
      "line": {
        "type": "Talk",
        "values": [
          {
            "key": "name",
            "value": "和哉"
          }
        ]
      }
    },
    {
      "lineNumber": 429,
      "shouldShift": false,
      "shift": 0,
      "line": {
        "text": "「あ、ああ。もちろん」\r\n"
      }
    },
    {
      "lineNumber": 434,
      "shouldShift": false,
      "shift": 0,
      "line": {
        "type": "Talk",
        "values": [
          {
            "key": "name",
            "value": "心の声"
          }
        ]
      }
    },
    {
      "lineNumber": 435,
      "shouldShift": false,
      "shift": 0,
      "line": {
        "text": "絵麻ならともかく、弥恵が倒れるなんて珍しい。\r\n"
      }
    },
    {
      "lineNumber": 438,
      "shouldShift": false,
      "shift": 0,
      "line": {
        "type": "Talk",
        "values": [
          {
            "key": "name",
            "value": "和哉"
          }
        ]
      }
    },
    {
      "lineNumber": 439,
      "shouldShift": false,
      "shift": 0,
      "line": {
        "text": "「じゃ、じゃあちょっと行ってくるな、智花」\r\n"
      }
    },
    {
      "lineNumber": 445,
      "shouldShift": false,
      "shift": 0,
      "line": {
        "type": "Talk",
        "values": [
          {
            "key": "name",
            "value": "智花"
          },
          {
            "key": "voice",
            "value": "TM001076"
          }
        ]
      }
    },
    {
      "lineNumber": 446,
      "shouldShift": false,
      "shift": 0,
      "line": {
        "text": "「むぅぅぅぅ……」\r\n"
      }
    },
    {
      "lineNumber": 449,
      "shouldShift": false,
      "shift": 0,
      "line": {
        "type": "Talk",
        "values": [
          {
            "key": "name",
            "value": "和哉"
          }
        ]
      }
    },
    {
      "lineNumber": 450,
      "shouldShift": false,
      "shift": 0,
      "line": {
        "text": "「智花？」\r\n"
      }
    },
    {
      "lineNumber": 455,
      "shouldShift": false,
      "shift": 0,
      "line": {
        "type": "Talk",
        "values": [
          {
            "key": "name",
            "value": "智花"
          },
          {
            "key": "voice",
            "value": "TM001077"
          }
        ]
      }
    },
    {
      "lineNumber": 456,
      "shouldShift": false,
      "shift": 0,
      "line": {
        "text": "「わ、分かってるわよ！　行ってらっしゃい」\r\n"
      }
    },
    {
      "lineNumber": 459,
      "shouldShift": false,
      "shift": 0,
      "line": {
        "type": "Talk",
        "values": [
          {
            "key": "name",
            "value": "心の声"
          }
        ]
      }
    },
    {
      "lineNumber": 460,
      "shouldShift": false,
      "shift": 0,
      "line": {
        "text": "なぜか智花は急に不機嫌になってしまった。\r\n"
      }
    },
    {
      "lineNumber": 469,
      "shouldShift": false,
      "shift": 0,
      "line": {
        "type": "Talk",
        "values": [
          {
            "key": "name",
            "value": "絵麻"
          },
          {
            "key": "voice",
            "value": "EM000489"
          }
        ]
      }
    },
    {
      "lineNumber": 470,
      "shouldShift": false,
      "shift": 0,
      "line": {
        "text": "「お兄ちゃん」\r\n"
      }
    },
    {
      "lineNumber": 477,
      "shouldShift": false,
      "shift": 0,
      "line": {
        "type": "Talk",
        "values": [
          {
            "key": "name",
            "value": "心の声"
          }
        ]
      }
    },
    {
      "lineNumber": 478,
      "shouldShift": false,
      "shift": 0,
      "line": {
        "text": "くいくい、と絵麻に服の裾を引っ張られる。\r\n"
      }
    },
    {
      "lineNumber": 481,
      "shouldShift": false,
      "shift": 0,
      "line": {
        "type": "Talk",
        "values": [
          {
            "key": "name",
            "value": "和哉"
          }
        ]
      }
    },
    {
      "lineNumber": 482,
      "shouldShift": false,
      "shift": 0,
      "line": {
        "text": "「あ、ああ……」\r\n"
      }
    },
    {
      "lineNumber": 488,
      "shouldShift": false,
      "shift": 0,
      "line": {
        "type": "Talk",
        "values": [
          {
            "key": "name",
            "value": "心の声"
          }
        ]
      }
    },
    {
      "lineNumber": 489,
      "shouldShift": false,
      "shift": 0,
      "line": {
        "text": "もう一度智花の方を見てから、俺は弥恵を抱えて\r\n"
      }
    },
    {
      "lineNumber": 490,
      "shouldShift": false,
      "shift": 0,
      "line": {
        "text": "妹たちの部屋へと向かった。\r\n"
      }
    },
    {
      "lineNumber": 502,
      "shouldShift": false,
      "shift": 0,
      "line": {
        "type": "Talk",
        "values": [
          {
            "key": "name",
            "value": "心の声"
          }
        ]
      }
    },
    {
      "lineNumber": 503,
      "shouldShift": false,
      "shift": 0,
      "line": {
        "text": "弥恵をベッドに寝かせてから、今度は飲み物を運ぶために\r\n"
      }
    },
    {
      "lineNumber": 504,
      "shouldShift": false,
      "shift": 0,
      "line": {
        "text": "リビングと妹双子の部屋を往復して……と、するうちに、\r\n"
      }
    },
    {
      "lineNumber": 505,
      "shouldShift": false,
      "shift": 0,
      "line": {
        "text": "いつのまにか智花はいなくなっていた。\r\n"
      }
    },
    {
      "lineNumber": 508,
      "shouldShift": false,
      "shift": 0,
      "line": {
        "type": "Talk",
        "values": [
          {
            "key": "name",
            "value": "心の声"
          }
        ]
      }
    },
    {
      "lineNumber": 509,
      "shouldShift": false,
      "shift": 0,
      "line": {
        "text": "洗濯物はもちろん、あの時濡れた床も綺麗に片付けられて\r\n"
      }
    },
    {
      "lineNumber": 510,
      "shouldShift": false,
      "shift": 0,
      "line": {
        "text": "いて、まるで先ほどのことは夢なんじゃないかと思える\r\n"
      }
    },
    {
      "lineNumber": 511,
      "shouldShift": false,
      "shift": 0,
      "line": {
        "text": "ほどだった。\r\n"
      }
    },
    {
      "lineNumber": 514,
      "shouldShift": false,
      "shift": 0,
      "line": {
        "type": "Talk",
        "values": [
          {
            "key": "name",
            "value": "心の声"
          }
        ]
      }
    },
    {
      "lineNumber": 515,
      "shouldShift": false,
      "shift": 0,
      "line": {
        "text": "智花がいないことを確認したあとも、弥恵の様子を確認\r\n"
      }
    },
    {
      "lineNumber": 516,
      "shouldShift": false,
      "shift": 0,
      "line": {
        "text": "したり、風呂に入ったりしているうちに、智花と顔を\r\n"
      }
    },
    {
      "lineNumber": 517,
      "shouldShift": false,
      "shift": 0,
      "line": {
        "text": "合わせる機会はついに訪れなかった。\r\n"
      }
    },
    {
      "lineNumber": 528,
      "shouldShift": false,
      "shift": 0,
      "line": {
        "type": "Talk",
        "values": [
          {
            "key": "name",
            "value": "心の声"
          }
        ]
      }
    },
    {
      "lineNumber": 529,
      "shouldShift": false,
      "shift": 0,
      "line": {
        "text": "風呂上がり、コップ１杯の水を飲みながら、さきほどの\r\n"
      }
    },
    {
      "lineNumber": 530,
      "shouldShift": false,
      "shift": 0,
      "line": {
        "text": "場所へ視線を向ける。\r\n"
      }
    },
    {
      "lineNumber": 533,
      "shouldShift": false,
      "shift": 0,
      "line": {
        "type": "Talk",
        "values": [
          {
            "key": "name",
            "value": "和哉"
          }
        ]
      }
    },
    {
      "lineNumber": 534,
      "shouldShift": false,
      "shift": 0,
      "line": {
        "text": "「本当に、夢だったのかもしれない……」\r\n"
      }
    },
    {
      "lineNumber": 543,
      "shouldShift": false,
      "shift": 0,
      "line": {
        "type": "Talk",
        "values": [
          {
            "key": "name",
            "value": "心の声"
          }
        ]
      }
    },
    {
      "lineNumber": 544,
      "shouldShift": false,
      "shift": 0,
      "line": {
        "text": "そう考えてもおかしくないほど、さっきの出来事は\r\n"
      }
    },
    {
      "lineNumber": 545,
      "shouldShift": false,
      "shift": 0,
      "line": {
        "text": "非現実的すぎた。\r\n"
      }
    },
    {
      "lineNumber": 548,
      "shouldShift": false,
      "shift": 0,
      "line": {
        "type": "Talk",
        "values": [
          {
            "key": "name",
            "value": "和哉"
          }
        ]
      }
    },
    {
      "lineNumber": 549,
      "shouldShift": false,
      "shift": 0,
      "line": {
        "text": "「………………」\r\n"
      }
    },
    {
      "lineNumber": 557,
      "shouldShift": false,
      "shift": 0,
      "line": {
        "type": "Talk",
        "values": [
          {
            "key": "name",
            "value": "心の声"
          }
        ]
      }
    },
    {
      "lineNumber": 558,
      "shouldShift": false,
      "shift": 0,
      "line": {
        "text": "俺は股間に集まってくる熱を振り払うように、部屋へと\r\n"
      }
    },
    {
      "lineNumber": 559,
      "shouldShift": false,
      "shift": 0,
      "line": {
        "text": "戻ることにした。\r\n"
      }
    },
    {
      "lineNumber": 574,
      "shouldShift": false,
      "shift": 0,
      "line": {
        "type": "Talk",
        "values": [
          {
            "key": "name",
            "value": "智花"
          },
          {
            "key": "voice",
            "value": "TM001078"
          }
        ]
      }
    },
    {
      "lineNumber": 575,
      "shouldShift": false,
      "shift": 0,
      "line": {
        "text": "「っぅ……！」\r\n"
      }
    },
    {
      "lineNumber": 578,
      "shouldShift": false,
      "shift": 0,
      "line": {
        "type": "Talk",
        "values": [
          {
            "key": "name",
            "value": "心の声"
          }
        ]
      }
    },
    {
      "lineNumber": 579,
      "shouldShift": false,
      "shift": 0,
      "line": {
        "text": "部屋に入ると、勉強机に腰掛けていた智花がびくっと\r\n"
      }
    },
    {
      "lineNumber": 580,
      "shouldShift": false,
      "shift": 0,
      "line": {
        "text": "跳ねた。\r\n"
      }
    },
    {
      "lineNumber": 583,
      "shouldShift": false,
      "shift": 0,
      "line": {
        "type": "Talk",
        "values": [
          {
            "key": "name",
            "value": "和哉"
          }
        ]
      }
    },
    {
      "lineNumber": 584,
      "shouldShift": false,
      "shift": 0,
      "line": {
        "text": "「あ……っと、その……」\r\n"
      }
    },
    {
      "lineNumber": 587,
      "shouldShift": false,
      "shift": 0,
      "line": {
        "type": "Talk",
        "values": [
          {
            "key": "name",
            "value": "心の声"
          }
        ]
      }
    },
    {
      "lineNumber": 588,
      "shouldShift": false,
      "shift": 0,
      "line": {
        "text": "智花の過剰な反応に感化されたように、俺の方でも言葉が\r\n"
      }
    },
    {
      "lineNumber": 589,
      "shouldShift": false,
      "shift": 0,
      "line": {
        "text": "出せなくなってしまう。\r\n"
      }
    },
    {
      "lineNumber": 595,
      "shouldShift": false,
      "shift": 0,
      "line": {
        "type": "Talk",
        "values": [
          {
            "key": "name",
            "value": "智花"
          },
          {
            "key": "voice",
            "value": "TM001079"
          }
        ]
      }
    },
    {
      "lineNumber": 596,
      "shouldShift": false,
      "shift": 0,
      "line": {
        "text": "「あっ……そ、その……弥恵は大丈夫だったの？」\r\n"
      }
    },
    {
      "lineNumber": 599,
      "shouldShift": false,
      "shift": 0,
      "line": {
        "type": "Talk",
        "values": [
          {
            "key": "name",
            "value": "和哉"
          }
        ]
      }
    },
    {
      "lineNumber": 600,
      "shouldShift": false,
      "shift": 0,
      "line": {
        "text": "「あ、ああ、うん。恥ずかしさが限界を超えたせい、とか\r\n"
      }
    },
    {
      "lineNumber": 601,
      "shouldShift": false,
      "shift": 0,
      "line": {
        "text": "　なんとか言ってたな」\r\n"
      }
    },
    {
      "lineNumber": 606,
      "shouldShift": false,
      "shift": 0,
      "line": {
        "type": "Talk",
        "values": [
          {
            "key": "name",
            "value": "智花"
          },
          {
            "key": "voice",
            "value": "TM001080"
          }
        ]
      }
    },
    {
      "lineNumber": 607,
      "shouldShift": false,
      "shift": 0,
      "line": {
        "text": "「そう……恥ずかしさ、ね」\r\n"
      }
    },
    {
      "lineNumber": 610,
      "shouldShift": false,
      "shift": 0,
      "line": {
        "type": "Talk",
        "values": [
          {
            "key": "name",
            "value": "心の声"
          }
        ]
      }
    },
    {
      "lineNumber": 611,
      "shouldShift": false,
      "shift": 0,
      "line": {
        "text": "不機嫌、ついではっとしたように目を見開いて、次に赤面、\r\n"
      }
    },
    {
      "lineNumber": 612,
      "shouldShift": false,
      "shift": 0,
      "line": {
        "text": "そしてまた不機嫌——智花の表情がくるくると変わる。\r\n"
      }
    },
    {
      "lineNumber": 617,
      "shouldShift": false,
      "shift": 0,
      "line": {
        "type": "Talk",
        "values": [
          {
            "key": "name",
            "value": "智花"
          },
          {
            "key": "voice",
            "value": "TM001081"
          }
        ]
      }
    },
    {
      "lineNumber": 618,
      "shouldShift": false,
      "shift": 0,
      "line": {
        "text": "「…………なにも、抱きしめなくても良かったんじゃない\r\n"
      }
    },
    {
      "lineNumber": 619,
      "shouldShift": false,
      "shift": 0,
      "line": {
        "text": "　かしら？」\r\n"
      }
    },
    {
      "lineNumber": 622,
      "shouldShift": false,
      "shift": 0,
      "line": {
        "type": "Talk",
        "values": [
          {
            "key": "name",
            "value": "心の声"
          }
        ]
      }
    },
    {
      "lineNumber": 623,
      "shouldShift": false,
      "shift": 0,
      "line": {
        "text": "やがて、智花の表情はジトっとしたものに固定された。\r\n"
      }
    },
    {
      "lineNumber": 626,
      "shouldShift": false,
      "shift": 0,
      "line": {
        "type": "Talk",
        "values": [
          {
            "key": "name",
            "value": "和哉"
          }
        ]
      }
    },
    {
      "lineNumber": 627,
      "shouldShift": false,
      "shift": 0,
      "line": {
        "text": "「抱き締めるって……弥恵のことか？」\r\n"
      }
    },
    {
      "lineNumber": 633,
      "shouldShift": false,
      "shift": 0,
      "line": {
        "type": "Talk",
        "values": [
          {
            "key": "name",
            "value": "智花"
          },
          {
            "key": "voice",
            "value": "TM001082"
          }
        ]
      }
    },
    {
      "lineNumber": 634,
      "shouldShift": false,
      "shift": 0,
      "line": {
        "text": "「そ、そうよ。なにも誤魔化すためとはいえ……」\r\n"
      }
    },
    {
      "lineNumber": 637,
      "shouldShift": false,
      "shift": 0,
      "line": {
        "type": "Talk",
        "values": [
          {
            "key": "name",
            "value": "心の声"
          }
        ]
      }
    },
    {
      "lineNumber": 638,
      "shouldShift": false,
      "shift": 0,
      "line": {
        "text": "そこまで言って、また表情がくるくると、赤くなったり\r\n"
      }
    },
    {
      "lineNumber": 639,
      "shouldShift": false,
      "shift": 0,
      "line": {
        "text": "青くなったりと忙しく変わる。\r\n"
      }
    },
    {
      "lineNumber": 645,
      "shouldShift": false,
      "shift": 0,
      "line": {
        "type": "Talk",
        "values": [
          {
            "key": "name",
            "value": "智花"
          },
          {
            "key": "voice",
            "value": "TM001083"
          }
        ]
      }
    },
    {
      "lineNumber": 646,
      "shouldShift": false,
      "shift": 0,
      "line": {
        "text": "「わ、私だって……まだ、あんな……」\r\n"
      }
    },
    {
      "lineNumber": 649,
      "shouldShift": false,
      "shift": 0,
      "line": {
        "type": "Talk",
        "values": [
          {
            "key": "name",
            "value": "心の声"
          }
        ]
      }
    },
    {
      "lineNumber": 650,
      "shouldShift": false,
      "shift": 0,
      "line": {
        "text": "また不機嫌に戻って、もごもごと呟いたかと思うと、\r\n"
      }
    },
    {
      "lineNumber": 651,
      "shouldShift": false,
      "shift": 0,
      "line": {
        "text": "今度は泣きそうな表情で俺を見上げる。\r\n"
      }
    },
    {
      "lineNumber": 657,
      "shouldShift": false,
      "shift": 0,
      "line": {
        "type": "Talk",
        "values": [
          {
            "key": "name",
            "value": "智花"
          },
          {
            "key": "voice",
            "value": "TM001084"
          }
        ]
      }
    },
    {
      "lineNumber": 658,
      "shouldShift": false,
      "shift": 0,
      "line": {
        "text": "「か、和哉、あのね……」\r\n"
      }
    },
    {
      "lineNumber": 661,
      "shouldShift": false,
      "shift": 0,
      "line": {
        "type": "Talk",
        "values": [
          {
            "key": "name",
            "value": "和哉"
          }
        ]
      }
    },
    {
      "lineNumber": 662,
      "shouldShift": false,
      "shift": 0,
      "line": {
        "text": "「っ……な、なんだ？」\r\n"
      }
    },
    {
      "lineNumber": 671,
      "shouldShift": false,
      "shift": 0,
      "line": {
        "type": "Talk",
        "values": [
          {
            "key": "name",
            "value": "心の声"
          }
        ]
      }
    },
    {
      "lineNumber": 672,
      "shouldShift": false,
      "shift": 0,
      "line": {
        "text": "追い詰められたような真剣な表情に、さっきの智花の姿が\r\n"
      }
    },
    {
      "lineNumber": 673,
      "shouldShift": false,
      "shift": 0,
      "line": {
        "text": "ダブる。\r\n"
      }
    },
    {
      "lineNumber": 676,
      "shouldShift": false,
      "shift": 0,
      "line": {
        "type": "Talk",
        "values": [
          {
            "key": "name",
            "value": "和哉"
          }
        ]
      }
    },
    {
      "lineNumber": 677,
      "shouldShift": false,
      "shift": 0,
      "line": {
        "text": "「————っ」\r\n"
      }
    },
    {
      "lineNumber": 687,
      "shouldShift": false,
      "shift": 0,
      "line": {
        "type": "Talk",
        "values": [
          {
            "key": "name",
            "value": "智花"
          },
          {
            "key": "voice",
            "value": "TM001085"
          }
        ]
      }
    },
    {
      "lineNumber": 688,
      "shouldShift": false,
      "shift": 0,
      "line": {
        "text": "「ぅ……ぁぅ……」\r\n"
      }
    },
    {
      "lineNumber": 691,
      "shouldShift": false,
      "shift": 0,
      "line": {
        "type": "Talk",
        "values": [
          {
            "key": "name",
            "value": "心の声"
          }
        ]
      }
    },
    {
      "lineNumber": 692,
      "shouldShift": false,
      "shift": 0,
      "line": {
        "text": "きっと俺の顔が赤くなっているのだろう、智花もさっと\r\n"
      }
    },
    {
      "lineNumber": 693,
      "shouldShift": false,
      "shift": 0,
      "line": {
        "text": "顔を赤くした。\r\n"
      }
    },
    {
      "lineNumber": 698,
      "shouldShift": false,
      "shift": 0,
      "line": {
        "type": "Talk",
        "values": [
          {
            "key": "name",
            "value": "智花"
          },
          {
            "key": "voice",
            "value": "TM001086"
          }
        ]
      }
    },
    {
      "lineNumber": 699,
      "shouldShift": false,
      "shift": 0,
      "line": {
        "text": "「な、なんでもない……」\r\n"
      }
    },
    {
      "lineNumber": 704,
      "shouldShift": false,
      "shift": 0,
      "line": {
        "type": "Talk",
        "values": [
          {
            "key": "name",
            "value": "和哉"
          }
        ]
      }
    },
    {
      "lineNumber": 705,
      "shouldShift": false,
      "shift": 0,
      "line": {
        "text": "「いや、でも……智花……あのさ……」\r\n"
      }
    },
    {
      "lineNumber": 708,
      "shouldShift": false,
      "shift": 0,
      "line": {
        "type": "Talk",
        "values": [
          {
            "key": "name",
            "value": "心の声"
          }
        ]
      }
    },
    {
      "lineNumber": 709,
      "shouldShift": false,
      "shift": 0,
      "line": {
        "text": "今聞かないと、またあやふやになってしまいそうだ。\r\n"
      }
    },
    {
      "lineNumber": 712,
      "shouldShift": false,
      "shift": 0,
      "line": {
        "type": "Talk",
        "values": [
          {
            "key": "name",
            "value": "心の声"
          }
        ]
      }
    },
    {
      "lineNumber": 713,
      "shouldShift": false,
      "shift": 0,
      "line": {
        "text": "リビングでのことと、その前のトイレでのこと……\r\n"
      }
    },
    {
      "lineNumber": 716,
      "shouldShift": false,
      "shift": 0,
      "line": {
        "type": "Talk",
        "values": [
          {
            "key": "name",
            "value": "心の声"
          }
        ]
      }
    },
    {
      "lineNumber": 717,
      "shouldShift": false,
      "shift": 0,
      "line": {
        "text": "智花のあんな姿を見てなお、普通に接してもいいのか\r\n"
      }
    },
    {
      "lineNumber": 718,
      "shouldShift": false,
      "shift": 0,
      "line": {
        "text": "どうか……俺には分からなくなっている。\r\n"
      }
    },
    {
      "lineNumber": 723,
      "shouldShift": false,
      "shift": 0,
      "line": {
        "type": "Talk",
        "values": [
          {
            "key": "name",
            "value": "智花"
          },
          {
            "key": "voice",
            "value": "TM001087"
          }
        ]
      }
    },
    {
      "lineNumber": 724,
      "shouldShift": false,
      "shift": 0,
      "line": {
        "text": "「か、和哉……」\r\n"
      }
    },
    {
      "lineNumber": 727,
      "shouldShift": false,
      "shift": 0,
      "line": {
        "type": "Talk",
        "values": [
          {
            "key": "name",
            "value": "和哉"
          }
        ]
      }
    },
    {
      "lineNumber": 728,
      "shouldShift": false,
      "shift": 0,
      "line": {
        "text": "「あ、ああ……」\r\n"
      }
    },
    {
      "lineNumber": 734,
      "shouldShift": false,
      "shift": 0,
      "line": {
        "type": "Talk",
        "values": [
          {
            "key": "name",
            "value": "智花"
          },
          {
            "key": "voice",
            "value": "TM001088"
          }
        ]
      }
    },
    {
      "lineNumber": 735,
      "shouldShift": false,
      "shift": 0,
      "line": {
        "text": "「〜〜〜〜〜〜っ！」\r\n"
      }
    },
    {
      "lineNumber": 742,
      "shouldShift": false,
      "shift": 0,
      "line": {
        "type": "Talk",
        "values": [
          {
            "key": "name",
            "value": "智花"
          },
          {
            "key": "voice",
            "value": "TM001089"
          }
        ]
      }
    },
    {
      "lineNumber": 743,
      "shouldShift": false,
      "shift": 0,
      "line": {
        "text": "「わ、私明日早いから！　もう寝るっ！　お休みなさい！」\r\n"
      }
    },
    {
      "lineNumber": 746,
      "shouldShift": false,
      "shift": 0,
      "line": {
        "type": "Talk",
        "values": [
          {
            "key": "name",
            "value": "和哉"
          }
        ]
      }
    },
    {
      "lineNumber": 747,
      "shouldShift": false,
      "shift": 0,
      "line": {
        "text": "「え、おいっ、智花！？」\r\n"
      }
    },
    {
      "lineNumber": 752,
      "shouldShift": false,
      "shift": 0,
      "line": {
        "type": "Talk",
        "values": [
          {
            "key": "name",
            "value": "智花"
          },
          {
            "key": "voice",
            "value": "TM001090"
          }
        ]
      }
    },
    {
      "lineNumber": 753,
      "shouldShift": false,
      "shift": 0,
      "line": {
        "text": "「お や す み な さ いっ！！」\r\n"
      }
    },
    {
      "lineNumber": 760,
      "shouldShift": false,
      "shift": 0,
      "line": {
        "type": "Talk",
        "values": [
          {
            "key": "name",
            "value": "心の声"
          }
        ]
      }
    },
    {
      "lineNumber": 761,
      "shouldShift": false,
      "shift": 0,
      "line": {
        "text": "あっという間に智花が布団を被ってしまう。\r\n"
      }
    },
    {
      "lineNumber": 764,
      "shouldShift": false,
      "shift": 0,
      "line": {
        "type": "Talk",
        "values": [
          {
            "key": "name",
            "value": "和哉"
          }
        ]
      }
    },
    {
      "lineNumber": 765,
      "shouldShift": false,
      "shift": 0,
      "line": {
        "text": "「…………お休み、智花」\r\n"
      }
    },
    {
      "lineNumber": 771,
      "shouldShift": false,
      "shift": 0,
      "line": {
        "type": "Talk",
        "values": [
          {
            "key": "name",
            "value": "智花"
          },
          {
            "key": "voice",
            "value": "TM001091"
          }
        ]
      }
    },
    {
      "lineNumber": 772,
      "shouldShift": false,
      "shift": 0,
      "line": {
        "text": "「ん…………」\r\n"
      }
    },
    {
      "lineNumber": 775,
      "shouldShift": false,
      "shift": 0,
      "line": {
        "type": "Talk",
        "values": [
          {
            "key": "name",
            "value": "心の声"
          }
        ]
      }
    },
    {
      "lineNumber": 776,
      "shouldShift": false,
      "shift": 0,
      "line": {
        "text": "布団の中で背を向けているらしい智花が、小さく頷く声。\r\n"
      }
    },
    {
      "lineNumber": 779,
      "shouldShift": false,
      "shift": 0,
      "line": {
        "type": "Talk",
        "values": [
          {
            "key": "name",
            "value": "心の声"
          }
        ]
      }
    },
    {
      "lineNumber": 780,
      "shouldShift": false,
      "shift": 0,
      "line": {
        "text": "きっと、それが智花の意志で……つまり『忘れろ』という\r\n"
      }
    },
    {
      "lineNumber": 781,
      "shouldShift": false,
      "shift": 0,
      "line": {
        "text": "ことなのだろう。\r\n"
      }
    },
    {
      "lineNumber": 784,
      "shouldShift": false,
      "shift": 0,
      "line": {
        "type": "Talk",
        "values": [
          {
            "key": "name",
            "value": "和哉"
          }
        ]
      }
    },
    {
      "lineNumber": 785,
      "shouldShift": false,
      "shift": 0,
      "line": {
        "text": "「………………」\r\n"
      }
    },
    {
      "lineNumber": 788,
      "shouldShift": false,
      "shift": 0,
      "line": {
        "type": "Talk",
        "values": [
          {
            "key": "name",
            "value": "心の声"
          }
        ]
      }
    },
    {
      "lineNumber": 789,
      "shouldShift": false,
      "shift": 0,
      "line": {
        "text": "いくら忘れる努力をしようとは思っても、智花を\r\n"
      }
    },
    {
      "lineNumber": 790,
      "shouldShift": false,
      "shift": 0,
      "line": {
        "text": "意識せずにはいられないだろう。\r\n"
      }
    },
    {
      "lineNumber": 793,
      "shouldShift": false,
      "shift": 0,
      "line": {
        "type": "Talk",
        "values": [
          {
            "key": "name",
            "value": "心の声"
          }
        ]
      }
    },
    {
      "lineNumber": 794,
      "shouldShift": false,
      "shift": 0,
      "line": {
        "text": "どうにか熱を薄れさせるために、俺は勉強机へと座った。\r\n"
      }
    },
    {
      "lineNumber": 797,
      "shouldShift": false,
      "shift": 0,
      "line": {
        "type": "Talk",
        "values": [
          {
            "key": "name",
            "value": "心の声"
          }
        ]
      }
    },
    {
      "lineNumber": 798,
      "shouldShift": false,
      "shift": 0,
      "line": {
        "text": "この一晩だけはせめて、ベッドに入るのは止めておこう……\r\n"
      }
    },
    {
      "lineNumber": 801,
      "shouldShift": false,
      "shift": 0,
      "line": {
        "type": "Talk",
        "values": [
          {
            "key": "name",
            "value": "心の声"
          }
        ]
      }
    },
    {
      "lineNumber": 802,
      "shouldShift": false,
      "shift": 0,
      "line": {
        "text": "そう思い、俺はそのまま目を瞑った。\r\n"
      }
    }
  ]
}